{"Pos_0:Pos_2_GA": 0.0, "Pos_0:Pos_1:Pos_2:Pos_3_TTAA": 0.0, "Pos_0:Pos_1:Pos_3_ATC": 0.0, "Pos_0:Pos_1:Pos_2:Pos_3_GCAG": 0.016123546663919835, "Pos_0:Pos_1:Pos_2:Pos_3_CATC": 0.03654854225593247, "Pos_0:Pos_2:Pos_3_CAT": 0.0, "Pos_0:Pos_1:Pos_2:Pos_3_GACT": 0.0, "Pos_0:Pos_1:Pos_3_CTG": 0.0, "Pos_0:Pos_1:Pos_2:Pos_3_ACCT": 0.0, "Pos_0:Pos_1:Pos_2:Pos_3_CGAA": -0.028052160219694533, "Pos_1:Pos_3_GA": 0.0, "Pos_0:Pos_1:Pos_2_ATC": 0.0, "Pos_0:Pos_1:Pos_2:Pos_3_TTAT": 0.0, "Pos_0:Pos_2_TG": 0.0, "Pos_0:Pos_1:Pos_3_CGG": -0.10311254355778808, "Pos_1_A": 0.0, "Pos_0:Pos_2:Pos_3_TGA": 0.0, "Pos_0:Pos_1:Pos_2:Pos_3_CAGA": 0.0, "Pos_0:Pos_1:Pos_3_CGC": 0.0, "Pos_0:Pos_1:Pos_2_GGC": 0.02766060685055048, "Pos_0:Pos_1:Pos_2:Pos_3_TCGT": -0.007000256427519878, "Pos_0:Pos_1:Pos_2:Pos_3_TGTA": -0.0030939930137615, "Pos_0:Pos_2:Pos_3_GGC": 0.0, "Pos_0:Pos_1:Pos_2:Pos_3_TGGG": 0.0, "Pos_0:Pos_1:Pos_2:Pos_3_ATGC": -0.0219727554772446, "Pos_1:Pos_2:Pos_3_GTC": 0.0, "Pos_1:Pos_2:Pos_3_GAG": 0.0, "Pos_0:Pos_1:Pos_2_CTT": -0.001440138755802277, "Pos_0:Pos_1:Pos_2:Pos_3_CTGT": 0.059783876207562814, "Pos_0:Pos_1:Pos_2:Pos_3_TACA": 0.0, "Pos_0:Pos_1:Pos_2:Pos_3_GTTC": 0.0, "Pos_0:Pos_2:Pos_3_CCG": 0.0, "Pos_0:Pos_2:Pos_3_TAA": 0.0, "Pos_0:Pos_2:Pos_3_TTG": 0.0, "Pos_0:Pos_1:Pos_2_CGA": -0.04140195764276303, "Pos_0:Pos_1:Pos_2:Pos_3_CTAT": -0.08095359357243541, "Pos_0:Pos_1:Pos_2:Pos_3_GAAT": 0.003054161796761137, "Pos_0:Pos_1:Pos_3_AGC": 0.0, "Pos_0:Pos_1:Pos_2:Pos_3_TTAG": -0.005089620416054452, "CtoT": -0.34496738238014624, "Pos_1:Pos_2:Pos_3_CTG": 2.0602389609480193e-05, "Pos_1:Pos_2_TG": 0.0, "Pos_0:Pos_1:Pos_2_CTC": 0.0, "Pos_0:Pos_1:Pos_3_ACG": 0.0, "Pos_1_C": 0.0, "Pos_0:Pos_1:Pos_2:Pos_3_GATA": -0.0036013598231794557, "Pos_1:Pos_2:Pos_3_TTA": 0.0, "Pos_0:Pos_1:Pos_2:Pos_3_GGAA": 0.0, "Pos_0:Pos_1:Pos_2:Pos_3_GTAA": -0.15310157186214793, "Pos_0:Pos_1:Pos_2_GAG": 0.0, "Pos_0:Pos_1:Pos_2:Pos_3_AAGG": -0.009222115131383093, "Pos_0:Pos_1:Pos_2:Pos_3_AATG": 0.00036938904513455904, "Pos_3_C": 0.0, "Pos_0:Pos_1:Pos_2:Pos_3_CGTA": 0.02765906255561116, "Pos_0:Pos_1:Pos_2:Pos_3_CCAC": 0.0, "Pos_0:Pos_1:Pos_3_CGT": 0.0, "Pos_0:Pos_1:Pos_2:Pos_3_GGTC": 0.0, "Pos_1:Pos_2:Pos_3_GTG": 0.0, "Pos_0:Pos_3_TG": 0.0, "Pos_1:Pos_2_AG": 0.0, "Pos_0:Pos_1:Pos_2_TTT": 0.0, "Pos_0:Pos_3_AC": 0.0, "Pos_0:Pos_1:Pos_2_CGG": 0.0, "Pos_0_C": 0.0, "Pos_0:Pos_2:Pos_3_ATG": 0.029432322140212644, "Pos_0:Pos_1:Pos_2:Pos_3_GATG": 0.0, "Pos_0:Pos_1:Pos_2:Pos_3_TCGG": 0.0, "Pos_0:Pos_1:Pos_2:Pos_3_GCTG": 0.0, "Pos_0:Pos_1:Pos_2:Pos_3_TCGA": -0.06902864556664763, "AtoT": 0.3558162872422104, "Pos_1:Pos_2:Pos_3_TCG": -0.06764267456166399, "Pos_0:Pos_1:Pos_2:Pos_3_GGGT": -0.019584109328876498, "Pos_0:Pos_1:Pos_2:Pos_3_TGGA": 0.06606944113818465, "Pos_2_T": 0.011918308560434904, "Pos_1:Pos_2:Pos_3_GGT": 0.0, "Pos_0:Pos_1:Pos_2_TGC": 0.0352870559783563, "Pos_0:Pos_1:Pos_3_GGT": 0.0, "Pos_1:Pos_2:Pos_3_TAC": 0.0, "Pos_0:Pos_1_GA": 0.0, "Pos_1:Pos_3_CA": -0.024541497119482655, "Pos_0:Pos_1:Pos_2:Pos_3_AGCT": 0.0, "Pos_0:Pos_1:Pos_2:Pos_3_CTCG": -0.04267315118936699, "Pos_2:Pos_3_GA": -0.020669815948296887, "Pos_0:Pos_1:Pos_2:Pos_3_ATCG": 0.0, "Pos_1:Pos_3_GG": 0.0, "Pos_1:Pos_2_TA": -0.020526242198756588, "Pos_1:Pos_2:Pos_3_CTT": 0.0, "Pos_0:Pos_2:Pos_3_CCA": 0.0, "Pos_0:Pos_1:Pos_3_TAG": 0.01391221676427469, "Pos_0:Pos_1:Pos_2:Pos_3_TGAC": 0.0948016035016627, "Pos_1:Pos_3_AG": 0.0, "Pos_0:Pos_1:Pos_2:Pos_3_CTAG": 0.0, "Pos_1:Pos_2_GT": 0.0, "Pos_0:Pos_1:Pos_2_GCA": 0.0, "Pos_0:Pos_2:Pos_3_ATC": 0.0, "Pos_2:Pos_3_CC": 0.0, "Pos_0:Pos_2:Pos_3_TCA": 0.0, "Pos_0:Pos_2:Pos_3_ACC": 0.0, "Pos_0:Pos_1:Pos_2:Pos_3_TCAA": -0.002664564486090645, "Pos_0:Pos_1:Pos_2:Pos_3_AGGC": 0.0, "Pos_0:Pos_2_GG": 0.0, "Pos_0:Pos_1:Pos_2:Pos_3_TAGT": 0.0, "Pos_0:Pos_1:Pos_2:Pos_3_GACC": 0.0, "Pos_0:Pos_2:Pos_3_CGT": 0.0, "Pos_0:Pos_1:Pos_2:Pos_3_GGCG": 0.0, "Pos_0:Pos_1:Pos_2:Pos_3_GCGG": 0.0, "CtoG": -0.4620017979747646, "Pos_0:Pos_1:Pos_2:Pos_3_GTTT": 0.12003318067874032, "Pos_0:Pos_1:Pos_2_TGG": 0.0, "Pos_0:Pos_1:Pos_2:Pos_3_TAAT": -0.027324377688623776, "Pos_0:Pos_1:Pos_2:Pos_3_CGAC": 0.0, "Pos_1:Pos_2:Pos_3_CGC": 0.0, "Pos_0:Pos_1:Pos_2:Pos_3_ACAC": -0.0631237866449004, "Pos_0:Pos_1:Pos_2:Pos_3_TATG": 0.0, "Pos_0:Pos_2_GC": 0.0, "Pos_0:Pos_2:Pos_3_GAG": 0.0, "Pos_1:Pos_3_AA": 0.0, "Pos_0:Pos_1:Pos_2:Pos_3_GCAC": -0.04608777192731746, "Pos_0:Pos_1:Pos_3_CAG": 0.0, "Pos_0:Pos_1:Pos_2:Pos_3_CGTC": 0.0, "Pos_0:Pos_1_CA": 0.0, "Pos_0:Pos_1:Pos_2_TGT": 0.0, "Pos_0:Pos_1:Pos_2_CAC": 0.0, "Pos_1:Pos_2_AT": 0.0, "Pos_0:Pos_1:Pos_2:Pos_3_GCTC": 0.04141842482342935, "Pos_0:Pos_2:Pos_3_GTT": 0.0, "Pos_1:Pos_3_GT": 0.005031551208993139, "Pos_0:Pos_1:Pos_2_TTA": -0.02517901082062301, "Pos_0:Pos_1:Pos_3_GAC": -0.030661397809038395, "Pos_0:Pos_2:Pos_3_AGG": 0.0, "Pos_0:Pos_1_AT": 0.0, "Pos_0:Pos_1:Pos_2_CGT": 0.0, "Pos_1:Pos_2:Pos_3_TCC": 0.002357062558843499, "Pos_0:Pos_1:Pos_3_TTA": 0.0, "Pos_0:Pos_1:Pos_2:Pos_3_ACCC": 0.0, "Pos_0:Pos_1:Pos_2:Pos_3_GCCG": -0.11455179673097218, "Pos_0:Pos_1:Pos_3_TAA": 0.0, "Pos_0:Pos_1:Pos_2:Pos_3_TAGA": 0.0, "Pos_0:Pos_1:Pos_2:Pos_3_GGAT": 0.0, "Pos_1:Pos_2:Pos_3_GCA": 0.0, "Pos_0:Pos_1:Pos_3_ACC": -0.11120675901253953, "Pos_0:Pos_1:Pos_2:Pos_3_AATT": 0.03685455688650119, "Pos_0:Pos_2:Pos_3_CGC": 0.0, "Pos_0:Pos_1:Pos_2:Pos_3_TTAC": -0.001592015010154318, "Pos_0:Pos_1:Pos_2:Pos_3_CAAA": 0.0, "Pos_0:Pos_1:Pos_2:Pos_3_ACGC": -0.009222679162434123, "Pos_0:Pos_2:Pos_3_TAC": 0.0, "Pos_1:Pos_2:Pos_3_CGA": 0.0, "Pos_2:Pos_3_GG": 0.0, "Pos_0:Pos_1:Pos_2_CAA": 0.0, "Pos_2:Pos_3_TC": 0.0, "Pos_0:Pos_1:Pos_2_GTC": -0.06643407942817378, "Pos_0:Pos_1:Pos_2_AAC": 0.0, "Pos_0:Pos_1:Pos_2:Pos_3_TAGC": 0.0, "Pos_0:Pos_2:Pos_3_ACG": 0.0, "Pos_0:Pos_1_TA": 0.0, "Pos_0:Pos_1:Pos_2:Pos_3_ATGT": -0.04811749916888042, "Pos_1_G": 0.2637287416706518, "Pos_0:Pos_3_GC": 0.0, "Pos_0:Pos_3_GG": 0.0, "Pos_0:Pos_1:Pos_2:Pos_3_TACT": 0.07441482557819167, "Pos_0:Pos_1:Pos_2:Pos_3_TCGC": 0.025521452895795584, "Pos_0:Pos_1:Pos_2:Pos_3_AACA": 0.0, "Pos_0:Pos_1:Pos_2:Pos_3_ACTG": 0.0, "Pos_0:Pos_1:Pos_2:Pos_3_GAAC": 0.022626766909504572, "AtoC": -0.021308023481654517, "Pos_0:Pos_2:Pos_3_AGA": -0.005869382159742192, "Pos_0:Pos_1:Pos_2:Pos_3_TTCA": 0.0, "Pos_0:Pos_1:Pos_2:Pos_3_AGTT": 0.0, "Pos_0:Pos_1:Pos_2:Pos_3_AGTC": 0.0, "Pos_0:Pos_1_AC": -0.010054317997106921, "Pos_0:Pos_1:Pos_2:Pos_3_ATAT": 0.010884536766136573, "Pos_0:Pos_1:Pos_2:Pos_3_TGGT": 0.0, "Pos_0:Pos_1:Pos_3_AAT": 0.020950972973007628, "Pos_1:Pos_2:Pos_3_GTA": 0.0, "Pos_0:Pos_1:Pos_2:Pos_3_GCGT": -0.05687313504949584, "Pos_0:Pos_1_CT": 0.0, "Pos_0:Pos_1:Pos_2:Pos_3_CGTT": 0.0, "Pos_0:Pos_1:Pos_2_GAC": 0.0, "Pos_0:Pos_1:Pos_2_TTG": 0.0, "Pos_0:Pos_1:Pos_2:Pos_3_TGTC": 0.0, "Pos_0:Pos_1:Pos_2:Pos_3_ACAG": -0.026705508223960388, "Pos_0:Pos_1:Pos_3_GGG": 0.0, "Pos_0:Pos_1:Pos_2_AAT": 0.0, "Pos_0:Pos_1:Pos_2:Pos_3_TGAT": 0.006260246793089268, "Pos_0:Pos_2:Pos_3_CAC": 0.0, "Pos_0:Pos_1:Pos_2:Pos_3_CTTG": 0.0, "Pos_0:Pos_2:Pos_3_ATT": 0.0, "Pos_2_G": -0.13797072792810836, "Pos_1:Pos_2:Pos_3_TTT": 0.0, "Pos_0:Pos_2:Pos_3_TTA": 0.0, "Pos_0:Pos_1:Pos_2:Pos_3_GGCA": 0.0, "Pos_1:Pos_2:Pos_3_GGA": 0.0, "Pos_1:Pos_2:Pos_3_AGG": 0.0, "Pos_0:Pos_2:Pos_3_CGA": 0.0, "Pos_0:Pos_2_GT": 0.0, "Pos_0:Pos_1:Pos_2:Pos_3_CCGG": 0.0, "Pos_0:Pos_3_AG": 0.0, "Pos_0:Pos_2_AG": -0.028355288052099043, "Pos_0:Pos_1:Pos_2:Pos_3_GGCT": 0.052284474896404726, "Pos_0:Pos_1:Pos_2:Pos_3_ATCT": 0.0, "Pos_0:Pos_1_GG": 0.0, "Pos_0:Pos_1:Pos_2:Pos_3_GAGG": 0.0, "Pos_0:Pos_1:Pos_2:Pos_3_GAAA": -0.026173167221386375, "Pos_0:Pos_1:Pos_2:Pos_3_ATTA": 0.0, "Pos_0:Pos_3_CC": -0.002311734544707484, "Pos_1:Pos_2:Pos_3_ATG": 0.0, "Pos_0:Pos_2:Pos_3_TCT": 0.04896321845302825, "Pos_0:Pos_1:Pos_2:Pos_3_GCCC": 0.0, "Pos_0:Pos_1:Pos_2:Pos_3_GCAT": -0.06039754062605651, "Pos_1:Pos_2:Pos_3_CAG": 0.0, "Pos_1:Pos_2:Pos_3_AAT": 0.0, "Pos_1:Pos_2:Pos_3_CTC": 0.0, "Pos_1:Pos_3_TA": 0.0, "Pos_0:Pos_1:Pos_2:Pos_3_TACG": 0.003242919186734276, "Pos_2:Pos_3_AC": 0.0, "Pos_0:Pos_1:Pos_2:Pos_3_TCAC": 0.0, "Pos_0:Pos_1:Pos_2:Pos_3_CACA": 0.0, "Pos_1:Pos_3_GC": 0.09851789705875437, "Pos_0:Pos_1:Pos_2_AGG": 0.0, "Pos_0:Pos_1:Pos_2_GGG": 0.0, "Pos_0:Pos_2:Pos_3_GCC": 0.0, "Pos_0:Pos_1:Pos_2:Pos_3_ATTG": -0.045497591180399005, "Pos_1:Pos_2_GC": 0.027052208034797465, "Pos_0:Pos_1:Pos_2:Pos_3_ACCA": 0.026315166148093184, "Pos_1:Pos_2_GA": 0.0, "Pos_0:Pos_1:Pos_2:Pos_3_ACGA": -0.040614338505469555, "Pos_0:Pos_1:Pos_2:Pos_3_ATCA": 0.025796761067767265, "Pos_1:Pos_2_AC": 0.0, "Pos_0:Pos_1:Pos_2:Pos_3_GCTA": 0.03830837931472287, "Pos_0:Pos_1:Pos_2:Pos_3_GGGC": 0.0, "Pos_1:Pos_2:Pos_3_GCG": 0.057467444347161036, "Pos_0:Pos_1:Pos_2:Pos_3_CTGA": 0.0, "Pos_1:Pos_2:Pos_3_CAC": 0.0, "Pos_1:Pos_2:Pos_3_GCT": 0.0, "Pos_0:Pos_1:Pos_3_GCT": -0.06011757003031693, "Pos_0:Pos_1:Pos_2_AAA": -0.01408067878773051, "Pos_0:Pos_1:Pos_2:Pos_3_TCCA": 0.007917332682928642, "Pos_1:Pos_3_CT": 0.0, "Pos_0:Pos_1:Pos_2_GGA": 0.0, "Pos_0:Pos_1:Pos_2:Pos_3_AGTG": 0.0, "Pos_0:Pos_2:Pos_3_CTT": 0.0344617678260969, "Pos_1:Pos_2:Pos_3_CTA": 0.0, "Pos_1:Pos_2:Pos_3_GAC": 0.0, "Pos_0:Pos_3_TA": 0.0, "Pos_0:Pos_1:Pos_3_CAC": 0.0, "Pos_0:Pos_2_AA": 0.0, "Pos_0:Pos_1:Pos_2:Pos_3_ACAA": 0.0, "Pos_2:Pos_3_AG": 0.0, "Pos_0:Pos_1:Pos_2_CGC": 0.0, "Pos_0:Pos_2_CT": 0.0, "Pos_0:Pos_1:Pos_2:Pos_3_CAAG": 0.06612166309678158, "Pos_0:Pos_2_TC": 0.04597315098617854, "Pos_0:Pos_1:Pos_2:Pos_3_GTGG": 0.020041231680969326, "Pos_1:Pos_2:Pos_3_AAC": 0.0, "Pos_0:Pos_1:Pos_2_CCA": 0.0, "Pos_0:Pos_1:Pos_2:Pos_3_GACG": 0.0, "Pos_0:Pos_1:Pos_2:Pos_3_AGCG": 0.0, "Pos_0:Pos_2:Pos_3_GAC": 0.0, "Pos_1:Pos_2:Pos_3_TGC": 0.0, "Pos_0:Pos_1:Pos_2:Pos_3_GGAG": 0.0, "Pos_0:Pos_1:Pos_2:Pos_3_CGGC": 0.0005130581458063361, "Pos_0:Pos_1:Pos_2_ATT": 0.0, "Pos_0:Pos_1_AG": 0.0, "Pos_0:Pos_3_TT": 0.0, "Pos_0:Pos_1:Pos_2_TCT": 0.058688551009928244, "Pos_0:Pos_1:Pos_2:Pos_3_AACT": 0.017340284615177146, "Pos_0:Pos_1:Pos_2:Pos_3_TGAG": 0.0, "Pos_0:Pos_1:Pos_3_CAT": 0.0, "Pos_0:Pos_1:Pos_2:Pos_3_CGCT": -0.014704377077584471, "Pos_0:Pos_1:Pos_3_AAG": 0.0, "Pos_1_T": 0.0, "Pos_0:Pos_1:Pos_2:Pos_3_ATGG": 0.0, "Pos_0:Pos_2:Pos_3_GGA": 0.0, "Pos_0:Pos_2:Pos_3_TCC": 0.0, "Pos_0:Pos_1:Pos_2:Pos_3_CTGG": 0.0, "Pos_0:Pos_1:Pos_2:Pos_3_ACGT": -0.05021143419123684, "Pos_0:Pos_2:Pos_3_CAA": 0.0, "Pos_1:Pos_2:Pos_3_TTG": 0.0, "Pos_0:Pos_2:Pos_3_CCC": 0.0, "Pos_0:Pos_3_CT": 0.0, "Pos_1:Pos_2:Pos_3_GTT": 0.0, "Pos_0:Pos_1:Pos_2:Pos_3_TAAC": 0.0, "Pos_0:Pos_1:Pos_2:Pos_3_CCGA": 0.015676455956412774, "Pos_0:Pos_1:Pos_2:Pos_3_CATT": 0.02991512125056466, "Pos_0:Pos_1:Pos_2:Pos_3_ACTT": 0.0, "Pos_0:Pos_1:Pos_2:Pos_3_TTGG": 0.0, "Pos_0:Pos_1:Pos_2:Pos_3_TGCT": 0.0, "Pos_0:Pos_1:Pos_2:Pos_3_GGGA": 0.0, "Pos_0:Pos_1:Pos_2:Pos_3_AGCC": 0.0, "Pos_0:Pos_1:Pos_2:Pos_3_AGGG": -0.01859606045281235, "Pos_0:Pos_1:Pos_2_TGA": 0.0, "Pos_0:Pos_1:Pos_2:Pos_3_GAGT": 0.0054148015534176575, "Pos_0:Pos_1:Pos_2:Pos_3_AGAG": 0.0, "Pos_1:Pos_2_CA": -0.003183160025900321, "Pos_0:Pos_1:Pos_3_GCG": 0.0, "Pos_0:Pos_1:Pos_2_CCG": 0.0, "Pos_0:Pos_1:Pos_2:Pos_3_GAGA": 0.0, "Pos_1:Pos_2:Pos_3_AGC": 0.0, "Pos_1:Pos_2:Pos_3_TGG": 0.035120425923519716, "Pos_0:Pos_1:Pos_3_GTC": 0.0, "Pos_0:Pos_2:Pos_3_TTT": 0.0, "Pos_0:Pos_1:Pos_3_ATT": 0.0, "Pos_0:Pos_1:Pos_2:Pos_3_GTCC": 0.0, "Pos_0:Pos_1:Pos_2_ACC": 0.0, "Pos_0:Pos_1:Pos_2:Pos_3_CAAC": -0.022226297532689926, "Pos_0:Pos_1:Pos_3_CGA": 0.0, "Pos_0:Pos_1:Pos_2:Pos_3_CCCC": 0.0, "Pos_0:Pos_2_CA": 0.0, "Pos_0:Pos_1:Pos_2:Pos_3_TAAG": 0.016081786285731578, "Pos_0:Pos_2:Pos_3_GCG": -0.012638730496774631, "Pos_1:Pos_2:Pos_3_GCC": 0.0, "Pos_0:Pos_2:Pos_3_TAT": 0.0018399536671373984, "Pos_0:Pos_1:Pos_2:Pos_3_GTAC": 0.0027628753951259603, "Pos_2:Pos_3_CA": 0.0, "Pos_1:Pos_2:Pos_3_CCC": 0.0, "Pos_0:Pos_1:Pos_2:Pos_3_CGAG": 0.0, "Pos_0:Pos_1:Pos_2:Pos_3_AGAT": 0.008396333595642524, "Pos_0:Pos_1:Pos_2:Pos_3_CACG": 0.0, "Pos_1:Pos_2_CC": 0.0, "Pos_0:Pos_1:Pos_2:Pos_3_CGGG": -0.017264807899327862, "Pos_0:Pos_1:Pos_3_TAT": 0.0, "Pos_0:Pos_1:Pos_2:Pos_3_TATA": 0.07650950971292743, "Pos_0:Pos_1:Pos_3_GTA": 0.0, "Pos_0:Pos_1:Pos_2:Pos_3_TATT": 0.0, "Pos_0:Pos_1:Pos_2:Pos_3_TCCG": -0.050035479856186074, "Pos_0:Pos_1:Pos_2:Pos_3_GTAT": -0.032375057530131444, "Pos_0:Pos_1:Pos_2:Pos_3_AAGA": 0.0, "Pos_1:Pos_2:Pos_3_GGC": 0.0, "Pos_0:Pos_1:Pos_2:Pos_3_TGGC": 0.0, "Pos_2:Pos_3_AA": 0.0, "Pos_0:Pos_1:Pos_2:Pos_3_TTCG": 0.034330223338279064, "Pos_0:Pos_1:Pos_2_GCC": 0.0, "Pos_0:Pos_1:Pos_3_TCT": 0.0, "Pos_0:Pos_1:Pos_2_AGT": 0.03992987987985974, "Pos_3_T": 0.0, "Pos_0:Pos_1:Pos_2:Pos_3_CTAA": 0.017412179947513054, "AtoG": 0.0, "Pos_0:Pos_1:Pos_2:Pos_3_TCTG": 0.0, "Pos_0:Pos_1_GT": 0.0, "TtoG": 0.02153543127619688, "Pos_0:Pos_1:Pos_2:Pos_3_GCGA": 0.0, "Pos_0:Pos_1_TG": 0.0, "Pos_0:Pos_1:Pos_2:Pos_3_TCAT": 0.0, "Pos_0:Pos_1:Pos_3_ATA": 0.0, "Pos_0:Pos_1:Pos_2:Pos_3_TAAA": 0.021021453378760827, "Pos_0:Pos_2:Pos_3_GTC": 0.0, "Pos_0:Pos_1:Pos_2:Pos_3_CACC": -0.01810569625339772, "Pos_0:Pos_1:Pos_3_AGG": 0.0, "Pos_0:Pos_2:Pos_3_CAG": 0.0, "Pos_0:Pos_1:Pos_2:Pos_3_GCCT": 0.0, "Pos_1:Pos_3_TC": 0.0, "Pos_0:Pos_1:Pos_2:Pos_3_GTCT": -0.0004804583925347894, "Pos_0:Pos_1:Pos_2:Pos_3_ATGA": 0.0030869322530142594, "Pos_1:Pos_2_TC": 0.0, "Pos_0:Pos_1:Pos_2:Pos_3_TGCA": 0.0, "Pos_0:Pos_1:Pos_2:Pos_3_AGAC": 0.0, "Pos_0:Pos_2:Pos_3_CTC": 0.0, "Pos_0:Pos_1:Pos_2:Pos_3_TCAG": -0.00021984529883053197, "Pos_0:Pos_1:Pos_2_TAG": -0.1862896705197688, "Pos_0:Pos_1:Pos_2_CAG": 0.0, "Pos_0:Pos_1:Pos_2_GCG": 0.0, "Pos_0:Pos_1:Pos_3_TGT": 0.08096914579398945, "Pos_1:Pos_2:Pos_3_ATC": 0.0, "Pos_0:Pos_1:Pos_2_CCC": 0.0, "Pos_0:Pos_2_TA": 0.0, "Pos_0:Pos_2:Pos_3_AAG": 0.0, "Pos_0:Pos_1:Pos_2:Pos_3_ACTC": 0.0, "Pos_0:Pos_1:Pos_2:Pos_3_GTAG": 0.0, "Pos_0:Pos_1:Pos_2:Pos_3_TCCT": 0.0, "Pos_1:Pos_2:Pos_3_AGT": 0.0, "Pos_0:Pos_1:Pos_2:Pos_3_TGAA": 0.0, "Pos_1:Pos_2:Pos_3_TAT": 0.0, "Pos_0:Pos_1:Pos_3_ACA": 0.0, "Pos_0:Pos_1:Pos_2:Pos_3_TTGT": 0.022442771487502292, "Pos_0:Pos_3_TC": 0.0, "Pos_1:Pos_2:Pos_3_TAA": 0.0, "Pos_0_G": 0.0, "Pos_0:Pos_1:Pos_2_GTA": 0.0, "Pos_1:Pos_3_AC": 0.0, "Pos_0:Pos_1_CC": 0.0, "Pos_1:Pos_2:Pos_3_TGA": 0.0, "Pos_0:Pos_1:Pos_2:Pos_3_TCTC": 0.0, "GtoA": -0.3973243811514254, "Pos_0:Pos_1:Pos_2:Pos_3_TTTG": 0.10621450087481504, "Pos_1:Pos_3_TT": 0.0, "Pos_0:Pos_1:Pos_2:Pos_3_TTCT": 0.0, "Pos_0:Pos_1:Pos_2:Pos_3_CGGT": -0.019772647709115743, "Pos_0:Pos_1:Pos_3_GGC": 0.0, "Pos_0:Pos_1:Pos_2:Pos_3_AACG": 0.0, "Pos_0:Pos_1:Pos_2:Pos_3_TGCC": 0.0, "Pos_2:Pos_3_TT": 0.0, "Pos_0:Pos_1:Pos_2:Pos_3_TTGC": 0.0, "Pos_1:Pos_3_CC": 0.0, "Pos_0:Pos_1:Pos_2_TAA": 0.0, "Pos_0:Pos_1:Pos_3_TCG": 0.0, "Pos_0:Pos_1:Pos_2:Pos_3_AAGT": 0.0, "Pos_0:Pos_1:Pos_3_ATG": 0.0, "Pos_0:Pos_1:Pos_2:Pos_3_TTTT": 0.0, "Pos_1:Pos_2:Pos_3_CCT": -0.009134045452039658, "Pos_0:Pos_1:Pos_3_ACT": -0.08527832064106429, "Pos_0:Pos_2:Pos_3_GCT": 0.0, "Pos_0:Pos_1:Pos_2:Pos_3_AAGC": 0.04838936343540307, "Pos_0:Pos_2:Pos_3_CGG": 0.0, "Pos_0:Pos_1:Pos_3_GCC": 0.0, "Pos_0:Pos_1:Pos_2:Pos_3_CTCA": 0.04371002118038086, "Pos_1:Pos_2_GG": -0.037776676551037495, "Pos_1:Pos_2_TT": 0.0, "Pos_0:Pos_1:Pos_2:Pos_3_CGTG": 0.0, "Pos_1:Pos_2:Pos_3_ATA": 0.0, "Pos_0:Pos_2:Pos_3_ATA": 0.0, "Pos_0:Pos_1:Pos_2:Pos_3_CTGC": 0.0, "Pos_0:Pos_1:Pos_2:Pos_3_ATCC": 0.0, "Pos_0:Pos_1:Pos_2_CTG": 0.0, "TtoA": 0.4460167805389428, "Pos_1:Pos_2:Pos_3_CAT": 0.0, "Pos_0:Pos_1:Pos_2:Pos_3_CCTG": 0.010926384068136927, "Pos_1:Pos_2:Pos_3_AAG": 0.0, "Pos_0:Pos_1:Pos_3_TCA": 0.0, "Pos_2:Pos_3_TG": 0.0, "Pos_0:Pos_1:Pos_2:Pos_3_CGAT": 0.0, "Pos_0:Pos_3_CA": 0.0, "Pos_0:Pos_2:Pos_3_ACT": 0.0037705164357557204, "Pos_0:Pos_1:Pos_2:Pos_3_CCCT": -0.03479626437460519, "Pos_0:Pos_1:Pos_3_CAA": 0.0, "Pos_1:Pos_2:Pos_3_CGT": -0.01272973162420212, "Pos_1:Pos_2_CG": -0.031316092525460956, "Pos_0:Pos_1:Pos_3_TGC": 0.0, "Pos_2_A": 0.0, "Pos_0:Pos_2_CG": 0.0, "Pos_0:Pos_1:Pos_2:Pos_3_ACTA": 0.0, "Pos_0:Pos_1:Pos_3_GTT": 0.0, "Pos_0:Pos_1:Pos_2:Pos_3_GCGC": -0.0391257446416725, "Pos_0:Pos_1:Pos_2:Pos_3_CGGA": -0.014299949655493475, "Pos_0:Pos_2:Pos_3_TTC": 0.0, "Pos_1:Pos_3_TG": 0.0, "Pos_0:Pos_1:Pos_2:Pos_3_TTGA": 0.0, "Pos_0:Pos_1:Pos_2_ATA": 0.0, "Pos_0:Pos_1:Pos_2:Pos_3_ATAC": -0.05572239477061654, "Pos_0:Pos_1:Pos_2:Pos_3_ACCG": -0.0292884520567814, "Pos_0:Pos_2:Pos_3_GAT": 0.0, "Pos_0:Pos_1:Pos_2:Pos_3_GAAG": -0.022174152421295872, "Pos_0:Pos_1:Pos_2:Pos_3_GTGT": -0.02824456201352623, "Pos_0:Pos_1:Pos_2:Pos_3_TATC": -0.007250241651953939, "Pos_1:Pos_2:Pos_3_GGG": 0.0, "Pos_0:Pos_1_AA": 0.0, "Pos_1:Pos_2:Pos_3_ACC": -0.03304832299957466, "Pos_0:Pos_1:Pos_3_GTG": -0.019352633288322076, "Pos_2_C": 0.0, "Pos_0:Pos_3_AA": 0.0, "Pos_0:Pos_1:Pos_2:Pos_3_GAGC": -0.054991650525116946, "Pos_0:Pos_2:Pos_3_TGG": 0.0, "Pos_0:Pos_1:Pos_2:Pos_3_GATT": -0.021420106539324885, "Pos_0:Pos_1:Pos_3_GAA": 0.0, "Pos_0:Pos_1:Pos_2:Pos_3_CCCA": 0.0, "Pos_0:Pos_1:Pos_3_GAG": 0.0, "Pos_0:Pos_1:Pos_2:Pos_3_CCGT": 0.0, "Pos_0:Pos_1:Pos_2:Pos_3_CAGT": -0.023460889148310314, "Pos_0:Pos_2_CC": 0.0, "Pos_0:Pos_1:Pos_2:Pos_3_CTCC": 0.0, "Pos_0:Pos_1:Pos_2:Pos_3_GTCG": 0.0, "Pos_3_A": 0.0, "Pos_1:Pos_2:Pos_3_GAA": 0.02655595311052501, "Pos_0:Pos_1:Pos_2:Pos_3_GGAC": 0.0, "Pos_0:Pos_1:Pos_2_GAT": -0.023293883899360292, "Pos_0:Pos_1_TT": 0.0, "Pos_0:Pos_3_AT": 0.0, "Pos_0:Pos_1:Pos_3_AAA": 0.0, "Pos_0:Pos_3_GA": 0.0, "Pos_0:Pos_2:Pos_3_GTA": 0.0, "Pos_0:Pos_1:Pos_2:Pos_3_CGCG": 0.045724957237818255, "Pos_0:Pos_1:Pos_2_GCT": 0.00015084792135655148, "Pos_0:Pos_1:Pos_2:Pos_3_CCAA": -0.0696369088517756, "Pos_0:Pos_1:Pos_2:Pos_3_AGAA": 0.0, "Pos_0:Pos_1:Pos_2:Pos_3_CAAT": 0.0, "Pos_0:Pos_2:Pos_3_TGT": -0.020612960752886957, "Pos_0:Pos_1:Pos_3_CTC": 0.0, "Pos_0:Pos_1:Pos_2:Pos_3_TACC": 0.0, "Pos_0:Pos_1:Pos_2:Pos_3_CCCG": 0.047856459344068035, "Pos_0:Pos_1:Pos_2:Pos_3_GGTA": 0.0, "Pos_0:Pos_1:Pos_2:Pos_3_AATA": -0.029890987246732066, "Pos_0:Pos_1:Pos_3_CCG": 0.0, "Pos_0:Pos_1:Pos_2:Pos_3_CCAT": 0.0, "Pos_1:Pos_2:Pos_3_ACT": 0.0, "Pos_0:Pos_2:Pos_3_GTG": 0.0, "Pos_0:Pos_1:Pos_3_TAC": 0.0, "Pos_0:Pos_1:Pos_2_AGA": 0.03235189701025992, "Pos_2:Pos_3_CG": 0.0, "Pos_1:Pos_2:Pos_3_TTC": 0.0, "Pos_0:Pos_1:Pos_2:Pos_3_AGGT": 0.0, "Pos_0:Pos_2:Pos_3_CCT": 0.0, "Pos_0:Pos_1:Pos_2:Pos_3_GCTT": 0.0, "Pos_0:Pos_1:Pos_2_AAG": 0.0, "Pos_1:Pos_2:Pos_3_TAG": 0.0, "Pos_0:Pos_1:Pos_2_GGT": 0.006680527076459618, "Pos_0:Pos_1:Pos_3_AAC": 0.0, "Pos_0:Pos_2:Pos_3_GGT": 0.0, "Pos_0:Pos_1:Pos_2:Pos_3_TCCC": -0.0280883647360915, "Pos_1:Pos_2:Pos_3_CGG": 0.0, "Pos_0:Pos_2:Pos_3_GGG": 0.0008818792541844628, "Pos_0:Pos_1:Pos_2:Pos_3_CACT": 0.0, "Pos_0:Pos_1:Pos_2_AGC": 0.0, "Pos_0:Pos_2_TT": 0.0, "Pos_0:Pos_1:Pos_2:Pos_3_CGCA": 0.0, "Pos_1:Pos_2:Pos_3_CCG": 0.0, "Pos_0:Pos_2:Pos_3_AGT": 0.0, "Pos_0:Pos_1:Pos_2:Pos_3_GTCA": -0.032330031763752105, "Pos_0:Pos_2:Pos_3_AGC": 0.0, "Pos_0:Pos_1:Pos_2:Pos_3_AAAG": -0.03151435127956691, "Pos_0:Pos_1:Pos_2_ACG": -0.047078720451920984, "Pos_0:Pos_1:Pos_2:Pos_3_AAAC": -0.003561528173907598, "Pos_1:Pos_2:Pos_3_CCA": 0.0, "Pos_0:Pos_1:Pos_2:Pos_3_ACGG": 0.0, "Pos_0:Pos_1:Pos_2:Pos_3_GCAA": 0.0, "Pos_0:Pos_1:Pos_2:Pos_3_CGCC": 0.0, "Pos_1:Pos_2_CT": 0.0, "Pos_0:Pos_1:Pos_2:Pos_3_TGTG": -0.0631579241902468, "Pos_0:Pos_2:Pos_3_GAA": 0.0, "Pos_0:Pos_1:Pos_2:Pos_3_GCCA": 0.0, "Pos_0:Pos_1:Pos_3_GAT": 0.0, "Pos_1:Pos_2:Pos_3_TCT": 0.0, "Pos_0:Pos_1:Pos_2:Pos_3_CTTT": 0.0, "Pos_0:Pos_1_TC": 0.0, "Pos_0:Pos_1:Pos_2:Pos_3_CTTA": 0.0, "Pos_0:Pos_1:Pos_2_ATG": 0.0, "Pos_0:Pos_1:Pos_2_TAT": 0.0, "Pos_0:Pos_1:Pos_2:Pos_3_CTAC": -0.17304819273694874, "Pos_0:Pos_1:Pos_2:Pos_3_ATAA": 0.0, "Pos_3_G": 0.0, "Pos_1:Pos_2:Pos_3_TCA": 0.0, "Pos_0:Pos_1:Pos_2_GAA": 0.0, "Pos_0:Pos_3_CG": 0.0, "Pos_0:Pos_2:Pos_3_AAT": 0.0, "Pos_0:Pos_1:Pos_2_TCC": 0.0, "Pos_0:Pos_2:Pos_3_TAG": -0.0022090379060586544, "Pos_0_T": 0.04182716935852414, "Pos_0:Pos_2:Pos_3_TGC": 0.0, "Pos_2:Pos_3_CT": 0.0, "Pos_0:Pos_1:Pos_2:Pos_3_TGCG": 0.0, "Pos_0:Pos_1:Pos_2:Pos_3_CTTC": -0.02393919709839619, "Pos_1:Pos_2:Pos_3_AAA": 0.0, "Pos_0:Pos_1:Pos_2:Pos_3_CCTT": 0.020138250821476796, "GtoT": 0.05722291676218793, "Pos_2:Pos_3_TA": 0.0, "Pos_0:Pos_2_AT": 0.0, "Pos_1:Pos_3_CG": 0.0, "Pos_0:Pos_1:Pos_2:Pos_3_CCTC": 0.0, "GC_feature": -0.1200613485619663, "Pos_0:Pos_1:Pos_3_GGA": 0.0, "Pos_0:Pos_1:Pos_2_TCG": 0.0, "Pos_0:Pos_1:Pos_2:Pos_3_AGGA": 0.0, "Pos_0:Pos_1:Pos_2:Pos_3_GTGC": 0.029554753108794914, "Pos_0:Pos_2:Pos_3_AAC": -0.02115241264455839, "Pos_0:Pos_1:Pos_2_CCT": 0.0, "Pos_0:Pos_2:Pos_3_TCG": 0.02415020448341748, "Pos_0:Pos_1:Pos_3_GCA": 0.0, "Pos_0:Pos_1:Pos_2:Pos_3_CATA": 0.04448490139707003, "Pos_0:Pos_1:Pos_2:Pos_3_CTCT": 0.06339913786870827, "GtoC": -0.4987529030934095, "Pos_0:Pos_1:Pos_2:Pos_3_GGGG": 0.0, "Pos_1:Pos_2_AA": 0.0, "Pos_1:Pos_2:Pos_3_ATT": 0.0, "Pos_0:Pos_1:Pos_2:Pos_3_GTGA": 0.0, "Pos_0:Pos_1:Pos_2_TCA": 0.0, "Pos_0:Pos_1:Pos_2:Pos_3_CCGC": 0.0, "Pos_0:Pos_1:Pos_3_AGA": 0.0, "Pos_0:Pos_1:Pos_2_CAT": 0.0, "Pos_0:Pos_1:Pos_2:Pos_3_TAGG": 0.0, "Pos_0:Pos_1:Pos_3_AGT": 0.0, "Pos_0:Pos_1:Pos_2_GTT": 0.0, "Pos_0:Pos_2:Pos_3_AAA": 0.0, "Pos_0:Pos_1:Pos_2:Pos_3_GACA": 0.0, "Pos_0:Pos_1:Pos_2:Pos_3_ATTC": 0.051765865248833656, "Pos_0:Pos_1:Pos_2:Pos_3_TTTA": 0.0, "Pos_0:Pos_1:Pos_3_TTC": 0.016705605057287836, "Pos_0:Pos_2_AC": 0.0, "Pos_0:Pos_1:Pos_2_GTG": 0.0, "Pos_0:Pos_1:Pos_2:Pos_3_TGTT": 0.07377127441475148, "Pos_0:Pos_1:Pos_2:Pos_3_TCTT": 0.02833166046125238, "Pos_0:Pos_1:Pos_2:Pos_3_TTCC": 0.011838659821000177, "Pos_0:Pos_1:Pos_2_ACT": 0.0, "Pos_0:Pos_1:Pos_2:Pos_3_AAAA": 0.0, "Pos_0:Pos_1:Pos_2:Pos_3_AATC": 0.0, "Pos_0:Pos_3_GT": 0.0, "Pos_0:Pos_1:Pos_2:Pos_3_TCTA": 0.0, "Pos_0:Pos_1:Pos_2_TTC": 0.0, "Pos_0:Pos_1:Pos_2:Pos_3_AAAT": 0.0, "Pos_0:Pos_1:Pos_2:Pos_3_CCTA": -0.03183481443769925, "Pos_0:Pos_1:Pos_3_CCC": 0.0, "Pos_0:Pos_1:Pos_2:Pos_3_ATAG": 0.0, "Pos_0:Pos_1:Pos_2:Pos_3_TTTC": 0.03846132950921915, "Pos_0:Pos_1:Pos_2:Pos_3_ACAT": 0.0, "Pos_0:Pos_1:Pos_3_CTA": 0.0002608671968047741, "Pos_0:Pos_1:Pos_3_TGA": 0.011631313045102946, "Pos_2:Pos_3_AT": 0.0, "Pos_0:Pos_1:Pos_2:Pos_3_CAGG": 0.019593340312612104, "Pos_0:Pos_1:Pos_3_CCA": 0.0, "Pos_0:Pos_2:Pos_3_ACA": 0.0, "Pos_1:Pos_2:Pos_3_ACA": 0.0, "Pos_1:Pos_2:Pos_3_GAT": 0.027172478330741566, "Pos_0:Pos_2:Pos_3_GCA": 0.0, "Pos_0:Pos_1:Pos_2:Pos_3_ATTT": 0.0, "Pos_0:Pos_1:Pos_3_TTG": 0.022409843243721497, "Pos_0:Pos_2:Pos_3_CTG": 0.0, "Pos_1:Pos_2:Pos_3_CAA": -0.01698753862241589, "Pos_0:Pos_1:Pos_2:Pos_3_GTTG": 0.0, "TtoC": 0.0, "Pos_0:Pos_1:Pos_2:Pos_3_AACC": 0.016170083061349594, "Pos_1:Pos_2:Pos_3_ACG": 0.0, "Pos_0:Pos_1:Pos_2_ACA": 0.0, "Pos_0:Pos_1:Pos_2:Pos_3_GGTT": 0.0, "Pos_1:Pos_2:Pos_3_TGT": 0.0, "Pos_0:Pos_1:Pos_2:Pos_3_CATG": -0.006428600216979675, "Pos_0:Pos_1:Pos_3_CTT": 0.0, "Pos_0_A": 0.0, "Pos_0:Pos_1:Pos_2:Pos_3_GGCC": 0.01003222384471458, "Pos_0:Pos_1:Pos_2:Pos_3_GATC": 0.0, "Pos_0:Pos_1:Pos_2:Pos_3_GGTG": 0.0012631826945130745, "Pos_1:Pos_2:Pos_3_AGA": 0.0, "Pos_0:Pos_1:Pos_2:Pos_3_AGTA": 0.042619207838679694, "Pos_0:Pos_1:Pos_2:Pos_3_AGCA": 0.0, "Pos_0:Pos_1:Pos_3_CCT": 0.0, "Pos_0:Pos_1_GC": 0.0, "Pos_0:Pos_2:Pos_3_CTA": 0.0, "Pos_1:Pos_3_AT": 0.0, "Pos_0:Pos_1:Pos_3_TTT": 0.0, "Pos_0:Pos_1:Pos_2:Pos_3_CAGC": 0.0, "Pos_0:Pos_1_CG": -0.1380074321894611, "Pos_0:Pos_1:Pos_2:Pos_3_GTTA": 0.0, "Pos_2:Pos_3_GT": 0.0, "Pos_0:Pos_1:Pos_2_CTA": 0.0, "Pos_2:Pos_3_GC": 0.0, "Pos_0:Pos_1:Pos_3_TGG": 0.0, "Pos_0:Pos_1:Pos_3_TCC": 0.0, "Pos_0:Pos_1:Pos_2:Pos_3_CCAG": 0.0, "Pos_0:Pos_1:Pos_2_TAC": 0.0, "CtoA": -0.044729981268431536}