{"Pos_2:Pos_3:Pos_4_ATT": 0.0, "Pos_1:Pos_3:Pos_4_TGT": -0.1969164939693946, "Pos_0:Pos_3:Pos_4_TGT": 0.0, "Pos_1:Pos_5_TT": 0.0, "Pos_0:Pos_3:Pos_4_TAG": 0.006825150684628999, "Pos_3:Pos_4_CA": 0.05866373320421441, "Pos_1:Pos_4_TC": 0.0, "Pos_2:Pos_3_GC": 0.0, "Pos_1:Pos_3:Pos_4_CGT": 0.062333739576861995, "Pos_1:Pos_3_TT": 0.0, "Pos_0:Pos_1:Pos_3_AGA": 0.0, "Pos_2:Pos_4:Pos_5_GTT": 0.0, "Pos_0:Pos_3:Pos_4_GGT": -0.04490657957096793, "Pos_0:Pos_1_TT": 0.0, "Pos_2:Pos_3:Pos_5_AAA": 0.0, "Pos_0:Pos_2:Pos_3_GCG": 0.0, "Pos_0:Pos_2:Pos_5_CGC": 0.0, "Pos_1:Pos_3:Pos_5_CTC": 0.0, "Pos_2:Pos_5_GT": 0.0, "Pos_2:Pos_3:Pos_4_CCC": 0.0, "Pos_0:Pos_1:Pos_4_GGT": 0.0, "Pos_0:Pos_1:Pos_4_ATT": 0.0, "Pos_0:Pos_3:Pos_4_TTG": 0.0, "Pos_0:Pos_1:Pos_2_CTG": 0.0, "Pos_0:Pos_2:Pos_4_GGG": 0.019746428828118123, "Pos_0:Pos_3_GC": 0.0, "Pos_1:Pos_3:Pos_5_GTG": 0.0, "Pos_0:Pos_4:Pos_5_ATG": 0.0, "Pos_0:Pos_2:Pos_5_GAA": 0.0, "Pos_3:Pos_4:Pos_5_AAA": 0.0, "Pos_1:Pos_2:Pos_3_GCG": -0.0614639319037007, "Pos_0:Pos_4:Pos_5_TAA": 0.0, "Pos_0:Pos_1:Pos_5_GTA": 0.0, "Pos_1:Pos_3:Pos_5_CTT": -0.0010758674835099835, "Pos_1:Pos_2:Pos_4_ATA": 0.0, "Pos_0:Pos_2:Pos_3_TCT": 0.0, "Pos_0:Pos_1:Pos_4_CAA": 0.06766051076045047, "Pos_1:Pos_2:Pos_4_AGG": 0.0, "Pos_4_C": 0.0, "Pos_1:Pos_2:Pos_5_GGG": 0.0, "Pos_0:Pos_2:Pos_3_CGG": 0.0, "Pos_1:Pos_2:Pos_5_TGA": 0.0, "Pos_0:Pos_3_CC": 0.0, "Pos_0:Pos_1:Pos_2_AAG": 0.0, "Pos_1:Pos_3:Pos_5_CGT": 0.0, "Pos_0:Pos_4:Pos_5_AGC": 0.0, "Pos_1:Pos_2:Pos_4_TGT": 0.026247260451566386, "Pos_0:Pos_1:Pos_2_CCC": 0.0, "Pos_0:Pos_2:Pos_4_GGC": 0.0, "Pos_0:Pos_1:Pos_3_TCT": 0.0, "Pos_2:Pos_3:Pos_4_AAG": 0.0, "Pos_0:Pos_1:Pos_2_TCG": -0.16450152608952207, "Pos_0:Pos_1:Pos_5_TTG": 0.0, "Pos_0:Pos_2:Pos_3_ATC": 0.0, "Pos_0:Pos_2:Pos_5_CGG": -0.06822250211169406, "Pos_2:Pos_4:Pos_5_AAT": 0.026884816805664895, "Pos_1:Pos_4:Pos_5_ATA": 0.0, "Pos_0:Pos_2:Pos_3_ACA": 0.0, "Pos_2:Pos_3:Pos_5_TAT": 0.0, "Pos_0:Pos_1:Pos_2_CGG": 0.0, "Pos_3:Pos_4:Pos_5_ATT": 0.0, "Pos_0:Pos_1:Pos_5_ATT": 0.0, "Pos_0:Pos_4:Pos_5_TGC": 0.0, "Pos_3:Pos_4:Pos_5_TTG": 0.0, "Pos_2:Pos_3:Pos_5_CTC": 0.003788634152714694, "Pos_1:Pos_2:Pos_3_GGT": 0.0, "Pos_0:Pos_3:Pos_5_TCA": 0.0, "Pos_2:Pos_3:Pos_5_GCT": 0.0, "Pos_3:Pos_5_TC": 0.0, "Pos_0:Pos_1:Pos_4_TGT": 0.0, "Pos_2:Pos_4:Pos_5_TAA": 0.0, "Pos_0:Pos_5_CA": 0.05105432725723507, "Pos_0:Pos_3:Pos_4_CCA": 0.0, "Pos_2:Pos_3:Pos_4_GGT": 0.0, "Pos_0:Pos_2:Pos_5_GGA": 0.0, "Pos_0:Pos_3_TT": 0.0, "Pos_0:Pos_2:Pos_5_CGA": 0.0, "Pos_0:Pos_1_CG": 0.0, "Pos_0:Pos_2:Pos_4_TGC": 0.0461565814458717, "Pos_0:Pos_1:Pos_3_CGG": 0.0, "Pos_1:Pos_2:Pos_3_TTG": 0.0, "Pos_0:Pos_1:Pos_2_TGT": 0.0, "Pos_0:Pos_1:Pos_5_CAG": 0.0, "Pos_1:Pos_2:Pos_5_CGA": 0.0, "Pos_0:Pos_1:Pos_3_GGG": 0.0, "Pos_0:Pos_2:Pos_3_AAC": -0.0016194161204439912, "Pos_3:Pos_4:Pos_5_CTT": 0.08282347252237758, "Pos_0:Pos_4:Pos_5_CCT": 0.0, "AtoG": 0.10711086255642713, "Pos_0:Pos_5_TT": 0.0, "Pos_0:Pos_1:Pos_3_CAC": 0.0, "Pos_1:Pos_4:Pos_5_CTG": 0.0, "Pos_0:Pos_4:Pos_5_GTC": 0.0, "Pos_0:Pos_3:Pos_5_GGC": 0.0005148305966156944, "Pos_0:Pos_2:Pos_4_TGA": 0.0, "Pos_1:Pos_2_CA": 0.03777429626572537, "Pos_0:Pos_1:Pos_2_TCA": 0.0, "GtoC": -1.9481536906132169, "Pos_1:Pos_3:Pos_5_ACA": -0.02650091763426773, "Pos_2:Pos_3:Pos_5_AGG": -0.1452020350152975, "Pos_0:Pos_1:Pos_4_CTG": 0.0, "Pos_3:Pos_4:Pos_5_TGG": -0.08511510578060699, "Pos_1:Pos_3:Pos_4_TTT": 0.0, "Pos_0:Pos_1:Pos_3_TGG": 0.0, "Pos_1:Pos_2:Pos_5_CGC": 0.0, "Pos_2:Pos_4_TT": 0.0, "Pos_0:Pos_1:Pos_4_GGG": 0.0, "Pos_0:Pos_1:Pos_5_GAT": 0.0, "Pos_0:Pos_1:Pos_2_TGA": 0.0, "Pos_0:Pos_5_CG": 0.0, "Pos_0:Pos_3:Pos_4_GCG": 0.0, "Pos_0:Pos_1:Pos_3_CAT": 0.0, "Pos_0:Pos_2:Pos_3_CGT": 0.06533339677857497, "Pos_1:Pos_2:Pos_3_ATT": 0.0, "Pos_4:Pos_5_GG": 0.0, "Pos_0:Pos_4:Pos_5_GAA": 0.0, "Pos_1:Pos_3:Pos_4_GAA": 0.0, "Pos_2:Pos_4:Pos_5_TGA": 0.0, "Pos_2:Pos_3:Pos_5_AAG": 0.0, "Pos_0:Pos_3:Pos_5_ACC": 0.0, "Pos_2:Pos_3:Pos_4_TTA": 0.0, "Pos_0:Pos_3:Pos_5_ATG": 0.05758525862742838, "Pos_0:Pos_2:Pos_4_ATT": -0.07490668454561995, "Pos_3:Pos_4_AA": 0.0, "Pos_1:Pos_4:Pos_5_CAT": 0.0, "Pos_3:Pos_4:Pos_5_ACC": 0.0, "Pos_1:Pos_2:Pos_3_CTC": 0.0, "Pos_0:Pos_2:Pos_3_CAT": 0.0, "Pos_3:Pos_5_TG": 0.0251525639199297, "Pos_2:Pos_4:Pos_5_TTT": 0.10313487498230528, "Pos_0:Pos_4:Pos_5_CGG": 0.0, "Pos_2:Pos_4:Pos_5_CAG": 0.01280087042874451, "Pos_0:Pos_3:Pos_4_TGC": 0.0, "Pos_0:Pos_3:Pos_5_GAG": -0.015171365767717212, "Pos_0:Pos_3:Pos_5_CCA": 0.0, "Pos_0:Pos_3:Pos_5_GGT": 0.0, "Pos_1:Pos_3:Pos_5_GCG": -0.013955217839274583, "Pos_1:Pos_2:Pos_5_CTA": 0.0, "Pos_1:Pos_2:Pos_4_TCG": 0.0, "Pos_2:Pos_4:Pos_5_AGA": 0.0, "Pos_0:Pos_1:Pos_3_CCG": 0.0, "Pos_1:Pos_2:Pos_5_AGG": 0.0, "Pos_0:Pos_2:Pos_5_ACA": 0.0, "Pos_0:Pos_2_CA": 0.0, "Pos_1:Pos_4:Pos_5_ATC": 0.07479308269823279, "Pos_0:Pos_3_GT": -0.04301078011221609, "Pos_1:Pos_3:Pos_4_TAA": 0.0, "Pos_3:Pos_4:Pos_5_CAC": 8.339521815515374e-05, "Pos_0:Pos_3:Pos_5_TGC": -0.09463475110916243, "Pos_0:Pos_1:Pos_4_CCT": 0.0, "Pos_0:Pos_1:Pos_5_CGT": 0.0835106779392164, "Pos_1:Pos_2_GA": 0.0, "Pos_2:Pos_3_TG": 0.0, "Pos_1:Pos_2:Pos_3_CCT": 0.0, "Pos_1:Pos_3:Pos_4_CAC": 0.0, "Pos_1:Pos_3:Pos_4_CTT": 0.0, "Pos_1:Pos_2:Pos_3_TAT": 0.0, "Pos_0:Pos_3:Pos_5_AGA": 0.0009879185494327688, "Pos_1:Pos_3:Pos_4_ACC": 0.0, "Pos_1:Pos_3:Pos_5_ACC": 0.0, "Pos_1:Pos_2:Pos_5_GTA": 0.0, "Pos_0:Pos_2:Pos_4_ACA": 0.0, "Pos_0:Pos_4:Pos_5_GGC": 0.0, "Pos_1:Pos_3:Pos_5_TGG": 0.0, "Pos_0:Pos_1:Pos_2_CAC": 0.0, "Pos_0:Pos_3_CG": -0.24597349957408818, "AtoT": 0.8393975896726732, "Pos_0:Pos_5_GC": 0.0, "Pos_0:Pos_3:Pos_4_AAT": -0.17952143978245488, "Pos_1:Pos_2:Pos_3_AGA": 0.0, "Pos_0:Pos_1:Pos_3_GCG": 0.0, "Pos_0:Pos_1:Pos_4_CAG": -0.054742408051847796, "Pos_0:Pos_1:Pos_3_CTC": 0.0, "Pos_1:Pos_2:Pos_4_AAA": 0.0, "Pos_0:Pos_5_AG": 0.0, "Pos_1:Pos_4:Pos_5_CTC": 0.0, "Pos_1:Pos_4:Pos_5_GGA": 0.033179638794288105, "Pos_2:Pos_5_TA": 0.0, "Pos_1:Pos_3:Pos_5_CAC": 0.0, "Pos_0:Pos_1:Pos_3_GAA": 0.0, "Pos_1:Pos_2:Pos_5_GCC": 0.0, "Pos_0:Pos_2:Pos_3_AAA": 0.0, "Pos_0:Pos_1:Pos_4_ATA": 0.036340332072896844, "Pos_0:Pos_5_TC": 0.0, "Pos_0:Pos_1:Pos_3_GGT": 0.0, "Pos_0:Pos_1:Pos_3_GCC": 0.0, "Pos_2:Pos_4:Pos_5_ATG": 0.0, "Pos_0:Pos_1:Pos_2_ACT": 0.0, "Pos_2:Pos_3:Pos_4_ATG": 0.08423313026716142, "Pos_4:Pos_5_CA": 0.0, "Pos_0:Pos_4:Pos_5_CGC": -0.06722784152943202, "Pos_1:Pos_2:Pos_5_GTG": 0.0, "Pos_0:Pos_1:Pos_4_ATC": 0.0, "Pos_1:Pos_2:Pos_3_TTA": 0.0, "Pos_3:Pos_5_TT": 0.0, "Pos_2:Pos_4:Pos_5_TGC": 0.0, "Pos_1:Pos_4:Pos_5_AAT": 0.0, "Pos_1:Pos_2:Pos_5_TTC": 0.18612444535417627, "Pos_0:Pos_1:Pos_4_CCG": 0.01353919132632571, "Pos_0:Pos_2:Pos_4_CTC": 0.0, "Pos_0:Pos_1:Pos_5_TGA": 0.0, "Pos_1:Pos_2:Pos_5_GAT": 0.0, "Pos_0:Pos_2:Pos_4_AGG": -0.2007475007288079, "Pos_0:Pos_1:Pos_3_ATA": 0.0, "Pos_1:Pos_3:Pos_4_TGG": 0.0, "Pos_3:Pos_4:Pos_5_CAA": 0.0, "Pos_1:Pos_2:Pos_5_TTG": 0.0, "Pos_1:Pos_4_TG": 0.0, "Pos_0:Pos_2:Pos_3_CTT": 0.0, "Pos_0:Pos_2:Pos_4_GAG": -0.022631164880560262, "Pos_1:Pos_3_CT": 0.0, "Pos_0:Pos_2:Pos_4_TCC": 0.0, "Pos_0:Pos_2:Pos_4_TTA": 0.0, "Pos_0:Pos_1:Pos_5_CTC": -0.07269950413612784, "Pos_1:Pos_2:Pos_3_TTC": 0.0, "Pos_0:Pos_1:Pos_3_TCA": 0.0, "Pos_1:Pos_2:Pos_5_TAT": 0.02079254193939535, "Pos_1:Pos_2_AT": 0.0, "Pos_0:Pos_2:Pos_4_ATG": 0.05458971507556065, "Pos_1:Pos_3:Pos_5_GTC": 0.0, "Pos_0:Pos_2:Pos_4_TGG": 0.0, "Pos_2:Pos_3:Pos_4_ATC": 0.0, "Pos_0:Pos_1:Pos_4_AGT": 0.0, "Pos_0:Pos_4_TA": 0.0, "Pos_1:Pos_2:Pos_3_TGC": 0.0, "Pos_0:Pos_1:Pos_3_AAT": 0.0, "Pos_1:Pos_2:Pos_3_AAA": 0.0, "Pos_0:Pos_2:Pos_3_AGA": 0.0, "Pos_2:Pos_5_GG": 0.0, "Pos_0:Pos_1:Pos_3_TGC": 0.05591112880647727, "Pos_0:Pos_2:Pos_5_ATG": 0.0, "Pos_3:Pos_4:Pos_5_CCA": 0.0, "Pos_1:Pos_2:Pos_4_TCT": 0.0, "Pos_0:Pos_2:Pos_5_ACT": 0.0, "Pos_1:Pos_3:Pos_4_AAA": 0.028064655997138532, "Pos_1:Pos_2:Pos_4_GAC": 0.0, "Pos_0:Pos_1:Pos_3_GCA": 0.0, "Pos_3:Pos_4:Pos_5_CTC": 0.0, "Pos_0:Pos_3:Pos_4_CTT": 0.0, "Pos_0:Pos_3:Pos_5_CCC": 0.0, "Pos_3_A": 0.0, "Pos_1:Pos_2:Pos_4_CTG": 0.0, "Pos_0:Pos_2_GC": 0.0, "Pos_0:Pos_3:Pos_4_CCT": 0.0, "Pos_0:Pos_1:Pos_5_ACA": 0.0, "Pos_0:Pos_1:Pos_4_TCG": 0.12925732928381833, "Pos_0:Pos_1:Pos_4_ACG": -0.04502076649852144, "Pos_0:Pos_2:Pos_4_GCT": 0.0, "Pos_0:Pos_3:Pos_5_CGG": 0.0, "Pos_2:Pos_4:Pos_5_GAA": 0.0, "Pos_1:Pos_5_CT": 0.0, "Pos_0:Pos_2:Pos_4_CAC": 0.0, "Pos_2:Pos_4_GA": 0.0, "Pos_0:Pos_3:Pos_4_GAT": 0.0, "Pos_1:Pos_3:Pos_4_CCA": 0.0, "Pos_0:Pos_1:Pos_3_AAC": 0.08073580085626693, "Pos_1:Pos_4_CG": 0.007869157874569198, "Pos_0:Pos_1:Pos_3_GTT": 0.0, "Pos_0:Pos_2:Pos_4_AAT": 0.0, "Pos_1:Pos_2:Pos_4_CGT": 0.0, "Pos_2:Pos_3:Pos_5_GTC": 0.0, "Pos_0:Pos_2:Pos_3_AGC": 0.00924132084313941, "Pos_2:Pos_5_CT": -0.02496312102340886, "Pos_0:Pos_3:Pos_5_GTA": 0.0, "Pos_1:Pos_3:Pos_5_TAC": 0.0, "Pos_0:Pos_3:Pos_5_CGA": 0.0, "Pos_2:Pos_3_GG": 0.0, "Pos_2:Pos_4:Pos_5_TGG": 0.0, "Pos_0:Pos_4:Pos_5_CTC": 0.0, "Pos_1:Pos_4:Pos_5_AGT": 0.0, "Pos_0:Pos_1:Pos_4_GTG": 0.0, "Pos_1:Pos_3:Pos_4_TTC": 0.0, "Pos_1:Pos_2:Pos_3_ACC": 0.0, "Pos_0:Pos_2:Pos_4_AGC": 0.03438941093397045, "Pos_1:Pos_2:Pos_5_CTT": 0.0, "Pos_3:Pos_4:Pos_5_TCA": 0.0, "Pos_0:Pos_3:Pos_5_TAA": 0.0, "Pos_0:Pos_1:Pos_2_GGC": 0.0, "Pos_0:Pos_3:Pos_5_AAT": 0.0, "Pos_0:Pos_3:Pos_4_CCG": 0.047156364364254175, "Pos_3:Pos_5_CT": 0.022430717487111076, "Pos_0:Pos_2:Pos_4_ACC": 0.0, "Pos_2:Pos_3_CC": 0.0, "Pos_1:Pos_2_TT": 0.0, "Pos_1:Pos_2:Pos_4_AGT": 0.0, "Pos_1:Pos_2:Pos_3_TCA": -0.12267027899521789, "Pos_0:Pos_2:Pos_3_TTC": 0.0, "Pos_1:Pos_2:Pos_5_ATA": 0.0, "Pos_1:Pos_3:Pos_4_TGA": 0.0, "Pos_0:Pos_1:Pos_5_CCT": 0.0, "Pos_2:Pos_3:Pos_4_CGA": 0.0, "Pos_0:Pos_3:Pos_4_TCC": 0.023794738926259072, "Pos_0:Pos_3:Pos_4_GCA": 0.010599234910308045, "Pos_1:Pos_4:Pos_5_GCG": 0.0, "Pos_0:Pos_1_GC": -0.009011749879499417, "Pos_0:Pos_3:Pos_4_GAA": 0.0, "Pos_2:Pos_3:Pos_4_GTG": 0.0, "Pos_1:Pos_3:Pos_5_CCT": 0.0, "Pos_0:Pos_2:Pos_5_GTA": 0.0, "Pos_0:Pos_1:Pos_2_TAG": 0.0, "Pos_0:Pos_3:Pos_5_AAA": 0.0, "Pos_1:Pos_3:Pos_5_GAT": 0.0, "Pos_0:Pos_1:Pos_2_AGA": 0.0, "Pos_1:Pos_2:Pos_4_CAG": 0.0, "Pos_1:Pos_4_GG": 0.0, "Pos_3:Pos_4:Pos_5_GCG": 0.0, "Pos_3_T": 0.05952592349081215, "Pos_3:Pos_4_CT": 0.060749013050424766, "Pos_0:Pos_2:Pos_5_ATA": 0.0, "Pos_0:Pos_3:Pos_4_GTT": 0.10104436313473124, "Pos_0:Pos_2:Pos_3_GAT": -0.1616080026729644, "Pos_0:Pos_2:Pos_4_CGA": -0.03795415034474653, "Pos_0:Pos_2:Pos_4_TGT": -0.0041862338831594155, "Pos_1:Pos_2:Pos_4_CGG": 0.0, "Pos_0:Pos_2:Pos_5_TGT": 0.0, "Pos_2:Pos_3:Pos_4_TTC": 0.0, "Pos_1:Pos_4_TT": 0.0, "Pos_0:Pos_1:Pos_5_GGA": 0.0, "Pos_1:Pos_3:Pos_5_TCC": -0.026718917664752616, "Pos_2:Pos_3:Pos_4_ACT": 0.0, "Pos_1:Pos_2:Pos_5_CCT": 0.03516646107962553, "Pos_2:Pos_3:Pos_5_CAC": 0.0, "Pos_0:Pos_5_CT": 0.0, "Pos_0:Pos_3_AG": 0.0, "Pos_2:Pos_3:Pos_5_TGG": 0.0, "Pos_1:Pos_2:Pos_3_ACT": 0.0, "Pos_1:Pos_4:Pos_5_TTC": 0.0, "Pos_1:Pos_2:Pos_5_TCT": 0.0, "Pos_2:Pos_3:Pos_5_CGG": 0.00941290611277041, "Pos_0:Pos_2_GT": 0.0, "Pos_0:Pos_2:Pos_3_GTA": 0.0, "Pos_0:Pos_2_CC": 0.0, "Pos_2:Pos_4:Pos_5_ATC": 0.0, "Pos_0:Pos_3:Pos_4_CAA": -0.17806224284124605, "Pos_1:Pos_3:Pos_4_CGC": 0.0, "Pos_0:Pos_1:Pos_4_GAG": 0.0, "Pos_0:Pos_4_CA": 0.0, "Pos_0:Pos_1:Pos_4_TGC": 0.0, "Pos_3:Pos_4:Pos_5_AGT": 0.0, "Pos_1:Pos_4:Pos_5_GCC": 0.0, "Pos_0:Pos_2:Pos_4_CTG": 0.0, "Pos_2:Pos_3:Pos_5_CCT": 0.015188695893356837, "Pos_1:Pos_3:Pos_4_TCA": 0.0, "Pos_1:Pos_2_AC": -0.017036416196585056, "Pos_0:Pos_1:Pos_4_GAC": 0.05451935885453252, "Pos_0:Pos_1:Pos_5_TTC": 0.0, "Pos_0:Pos_1:Pos_2_ACC": 0.0, "Pos_0:Pos_1:Pos_2_CTT": 0.1365430823875465, "Pos_0:Pos_3:Pos_5_ATA": 0.0, "Pos_0:Pos_1:Pos_3_CAG": 0.0, "Pos_0:Pos_2:Pos_5_ATC": 0.0, "Pos_1:Pos_2:Pos_4_GAT": 0.0, "Pos_0:Pos_1:Pos_2_TTC": -0.015929669465892925, "Pos_0:Pos_3:Pos_4_CGT": 0.0, "Pos_1:Pos_3:Pos_5_GGC": 0.08723746994416098, "Pos_2:Pos_4:Pos_5_CAA": 0.0, "Pos_1:Pos_3:Pos_5_TCG": 0.001117916913811315, "Pos_0:Pos_1:Pos_5_TTT": 0.0, "Pos_2:Pos_3:Pos_4_CTC": 0.018879116212255083, "Pos_3:Pos_4:Pos_5_ATC": 0.0, "Pos_3:Pos_4:Pos_5_AAG": 0.0, "Pos_0:Pos_1_GG": 0.0, "Pos_1:Pos_2:Pos_3_CGC": 0.018216759098820392, "Pos_1:Pos_2:Pos_3_GAC": 0.0, "Pos_1:Pos_2:Pos_4_AAG": 0.0, "Pos_0:Pos_2:Pos_3_CCG": -0.037037770839799346, "Pos_0:Pos_3:Pos_5_AGC": 0.0, "Pos_0:Pos_3:Pos_5_ATT": 0.0, "Pos_2:Pos_4_GG": 0.0, "Pos_0:Pos_1:Pos_5_GTT": 0.0, "Pos_1:Pos_2:Pos_5_AAG": 0.0, "Pos_0:Pos_2:Pos_4_AAG": 0.03149203484932146, "Pos_2_G": 0.25388750922051984, "Pos_0:Pos_4:Pos_5_GAT": 0.0569742029350895, "Pos_0:Pos_1:Pos_3_AAA": 0.0, "Pos_3:Pos_4:Pos_5_GAC": 0.0, "Pos_0:Pos_1:Pos_4_GTT": 0.0, "Pos_2:Pos_4:Pos_5_AGG": 0.0, "Pos_1:Pos_3:Pos_4_CTA": 0.0, "Pos_0:Pos_1:Pos_3_CCT": 0.0, "Pos_1:Pos_2:Pos_4_AGC": 0.043063580091396665, "Pos_0:Pos_2:Pos_4_CGC": 0.0, "Pos_0:Pos_1:Pos_5_GCC": 0.0, "Pos_1:Pos_3:Pos_4_CCC": 0.0, "Pos_1:Pos_4:Pos_5_CAG": 0.0, "Pos_2:Pos_4:Pos_5_CTG": 0.0, "Pos_2:Pos_3:Pos_5_CGA": 0.0, "Pos_0:Pos_3_AA": 0.0, "Pos_2:Pos_4:Pos_5_CTA": -0.049628268032373246, "Pos_1:Pos_3:Pos_5_GGT": 0.0, "Pos_0:Pos_1:Pos_2_GAA": 0.06322268621990212, "Pos_2:Pos_3:Pos_5_AGT": 0.0, "Pos_1:Pos_4:Pos_5_ACT": 0.05972993777525496, "Pos_0:Pos_1:Pos_4_TTA": 0.0, "Pos_1:Pos_2:Pos_4_CAC": 0.0, "Pos_1:Pos_3:Pos_5_TTG": 0.0, "Pos_0:Pos_2:Pos_3_CTA": 0.0, "Pos_1:Pos_2:Pos_5_TCG": 0.12128542086451173, "Pos_1:Pos_3:Pos_5_TGT": 0.0, "Pos_0:Pos_2:Pos_5_GCC": 0.0, "Pos_0:Pos_1:Pos_3_CGC": 0.0, "Pos_2:Pos_3:Pos_4_TGA": 0.0, "Pos_0:Pos_3:Pos_4_TAC": 0.0, "Pos_1:Pos_3:Pos_4_ACG": 0.0, "Pos_1:Pos_3:Pos_5_GGG": 0.0, "Pos_2:Pos_3:Pos_5_GCA": 0.0, "Pos_0:Pos_2:Pos_5_TTT": 0.0, "Pos_1:Pos_4_GT": 0.0, "Pos_2:Pos_3:Pos_4_GGC": 0.0, "Pos_0:Pos_2:Pos_3_GGG": 0.0, "Pos_0:Pos_2:Pos_4_CGG": 0.0, "CtoA": 0.0, "Pos_2:Pos_3_AG": 0.0, "Pos_0:Pos_3:Pos_5_GAC": -0.05789795200077613, "Pos_1:Pos_2:Pos_5_AGA": 0.0, "Pos_2_T": 0.0, "Pos_1:Pos_4:Pos_5_CGG": 0.0, "Pos_0:Pos_4:Pos_5_GCA": 0.0, "Pos_0:Pos_3:Pos_5_GAA": 0.04966024090496765, "Pos_0:Pos_3:Pos_4_ACA": 0.0, "Pos_2:Pos_3:Pos_5_ATC": 0.0, "Pos_0:Pos_2:Pos_3_TCC": 0.0, "Pos_0:Pos_1:Pos_4_GGC": -0.022187879361855723, "Pos_0:Pos_3:Pos_4_AGT": 0.07210414029654034, "Pos_1:Pos_3:Pos_4_GAC": 0.0, "Pos_0:Pos_2:Pos_4_CAT": 0.0, "Pos_1:Pos_3_AC": 0.0, "Pos_0:Pos_1:Pos_2_CAG": 0.0, "Pos_0:Pos_2:Pos_5_AGA": 0.0, "Pos_2:Pos_4:Pos_5_GGA": 0.0, "Pos_0:Pos_2:Pos_3_TGA": 0.009802998759755065, "Pos_3:Pos_4:Pos_5_CTA": 0.0, "Pos_2:Pos_4_TA": 0.0, "Pos_0:Pos_2:Pos_3_AAG": 0.0, "Pos_0:Pos_1:Pos_5_GCT": 0.0, "Pos_0:Pos_1:Pos_5_TAG": 0.0, "Pos_0:Pos_1:Pos_2_AAT": 0.0, "Pos_0:Pos_4:Pos_5_TTA": 0.0, "Pos_1:Pos_2:Pos_4_GTT": -0.005475518563445285, "Pos_1:Pos_4:Pos_5_ACC": 0.0, "Pos_0:Pos_2:Pos_3_CCT": 0.003708430903226725, "Pos_0:Pos_1:Pos_3_ACT": 0.0, "Pos_1:Pos_3:Pos_4_ATA": 0.0, "Pos_0:Pos_2:Pos_3_CCC": 0.0, "Pos_1:Pos_2:Pos_4_CTC": 0.0, "Pos_1:Pos_3:Pos_4_AAG": -0.00591449162555246, "Pos_0:Pos_2:Pos_4_GGA": -0.11769501749281389, "Pos_0:Pos_2:Pos_3_CGC": 0.0, "Pos_1:Pos_2:Pos_3_CAG": 0.0, "Pos_1:Pos_3_TG": 0.0, "Pos_0:Pos_1:Pos_5_ACG": 0.0, "Pos_0:Pos_1:Pos_5_GTC": 0.0, "Pos_0:Pos_1:Pos_3_TGA": 0.0, "Pos_0:Pos_2_AG": 0.0, "Pos_1:Pos_3:Pos_4_GCG": 0.0, "Pos_1:Pos_2:Pos_5_CCA": 0.0, "Pos_1:Pos_3:Pos_4_ACA": 0.0, "Pos_2:Pos_4:Pos_5_GCG": 0.0, "Pos_2:Pos_4_TG": 0.0, "Pos_0:Pos_5_AC": 0.08093940204475458, "Pos_0:Pos_2:Pos_4_GGT": 0.0, "Pos_1:Pos_2:Pos_4_CCG": 0.0, "Pos_0:Pos_1:Pos_3_CTT": 0.0, "Pos_2:Pos_3_TA": -0.0891117721619479, "Pos_1:Pos_3:Pos_4_GGC": -0.004198828638189572, "Pos_0:Pos_2:Pos_3_CTC": 0.0, "Pos_0:Pos_1:Pos_5_CGC": 0.04915530475593391, "Pos_0:Pos_2:Pos_4_AGA": 0.0, "Pos_1:Pos_3_GC": 0.0, "Pos_3:Pos_4:Pos_5_CCC": -0.04646514182630434, "Pos_0:Pos_1_CT": 0.0, "Pos_3:Pos_4:Pos_5_TTT": 0.0, "Pos_0:Pos_1_AG": 0.0, "Pos_0:Pos_1_TG": 0.0, "Pos_1:Pos_2:Pos_5_CAT": 0.0, "Pos_2:Pos_4:Pos_5_TGT": 0.0, "Pos_0:Pos_2:Pos_5_TCA": 0.2597682717680278, "Pos_0:Pos_3:Pos_4_ATT": 0.0, "Pos_2:Pos_3:Pos_5_TGA": 0.0, "Pos_2:Pos_3:Pos_5_GGG": 0.0, "Pos_0:Pos_4:Pos_5_CAC": 0.0, "Pos_0:Pos_1:Pos_5_TAA": 0.0, "Pos_0:Pos_4_CT": 0.0, "Pos_0:Pos_4:Pos_5_CAA": 0.0, "Pos_1:Pos_2:Pos_5_GTC": -0.004217378125612468, "Pos_0:Pos_2:Pos_3_GGA": 0.0, "Pos_2:Pos_3:Pos_5_ACT": 0.0, "Pos_2:Pos_4_GC": 0.0, "Pos_0:Pos_4:Pos_5_GTG": 0.0, "Pos_0:Pos_3:Pos_5_TTA": 0.0, "Pos_1:Pos_2:Pos_4_CTT": 0.0, "Pos_0:Pos_1:Pos_2_CGA": 0.0, "Pos_0:Pos_1:Pos_2_TCT": 0.0, "Pos_2:Pos_3:Pos_4_TAC": 0.0, "Pos_0:Pos_2:Pos_4_AGT": 0.0, "Pos_5_T": 0.0, "Pos_0:Pos_1:Pos_3_TTA": 0.18304987628504615, "Pos_0:Pos_2:Pos_3_GAA": 0.0, "Pos_2:Pos_3:Pos_4_AGG": 0.0, "Pos_0:Pos_3:Pos_5_CTA": 0.020330374477985153, "Pos_1:Pos_3:Pos_4_CGG": 0.0, "Pos_2:Pos_3:Pos_5_GGC": 0.0, "Pos_0:Pos_1:Pos_2_CCT": -0.03791873078800909, "Pos_2:Pos_3:Pos_5_ACC": -0.012561672268724202, "Pos_3:Pos_5_GA": 0.0, "Pos_0:Pos_3:Pos_5_TGA": -0.014111419648353375, "Pos_0:Pos_1:Pos_3_CCC": 0.0, "Pos_1:Pos_2:Pos_4_TCC": 0.0, "Pos_0:Pos_4_AT": 0.0, "Pos_1:Pos_5_TA": 0.0, "Pos_0:Pos_5_AA": 0.0, "Pos_1:Pos_2:Pos_5_GGA": -0.02153500030720436, "Pos_2:Pos_3:Pos_4_CTA": 0.0, "Pos_0:Pos_1:Pos_4_CAC": 0.0, "Pos_4_A": 0.0, "Pos_0:Pos_1:Pos_3_TAC": 0.0, "Pos_2:Pos_3:Pos_4_GAC": 0.0, "Pos_0:Pos_1:Pos_5_CTT": 0.0, "Pos_0:Pos_1:Pos_2_GTC": 0.0, "Pos_0:Pos_3:Pos_5_TCG": 0.0, "Pos_0:Pos_2:Pos_4_ATA": 0.0, "Pos_0:Pos_2:Pos_3_TTG": -0.09952904601000256, "Pos_1:Pos_2:Pos_3_GGC": 0.0, "Pos_1:Pos_4:Pos_5_TTA": 0.0, "Pos_0:Pos_1:Pos_2_AGG": 0.10356297258608163, "Pos_1:Pos_3:Pos_4_GGT": 0.0, "Pos_0:Pos_3:Pos_5_GAT": 0.0, "Pos_2:Pos_5_TC": 0.0, "Pos_0:Pos_1:Pos_2_CGT": 0.0, "Pos_2:Pos_3:Pos_5_TCG": 0.0, "Pos_1:Pos_2:Pos_3_TCG": 0.0, "Pos_1:Pos_3:Pos_5_TAG": 0.0, "Pos_0:Pos_1:Pos_5_CTG": 0.0, "Pos_0:Pos_1:Pos_3_GGC": 0.0, "Pos_1:Pos_3:Pos_5_ATG": 0.09265666628580282, "Pos_0:Pos_2:Pos_4_CCC": 0.0, "Pos_1:Pos_2:Pos_4_TTT": 0.0, "Pos_1:Pos_3:Pos_5_TAA": 0.0, "Pos_1:Pos_2:Pos_4_TCA": 0.0, "Pos_0:Pos_1:Pos_2_CAA": 0.0, "Pos_2:Pos_3:Pos_5_GCC": 0.043902152274509415, "Pos_0:Pos_4:Pos_5_ATC": 0.0, "Pos_2:Pos_4:Pos_5_CCA": 0.0, "Pos_2:Pos_4:Pos_5_CTC": 0.0, "Pos_1:Pos_2:Pos_3_GCA": 0.0, "Pos_2:Pos_4:Pos_5_CGT": 0.0, "Pos_1:Pos_5_GC": 0.0, "Pos_1:Pos_3:Pos_5_AAT": 0.0, "Pos_1:Pos_3_GA": 0.0, "Pos_0:Pos_1:Pos_5_TAT": 0.0, "Pos_0:Pos_3:Pos_4_ATG": 0.0, "Pos_2:Pos_3:Pos_5_TTG": 0.0, "Pos_0:Pos_1:Pos_2_AAA": 0.0, "Pos_0:Pos_2:Pos_5_CAC": 0.0, "Pos_1:Pos_2_GG": 0.0, "Pos_0:Pos_2:Pos_3_GCC": 0.0, "Pos_0:Pos_1:Pos_2_ACG": 0.0, "Pos_0:Pos_4:Pos_5_AGA": 0.0, "Pos_0:Pos_3_CA": 0.0, "Pos_0:Pos_5_TG": 0.0, "Pos_1:Pos_4:Pos_5_CTT": 0.03550825980922264, "Pos_1:Pos_2:Pos_4_GCG": 0.0, "Pos_0:Pos_1:Pos_2_CTA": 0.0, "Pos_0:Pos_2:Pos_5_TAA": 0.0, "Pos_1:Pos_2:Pos_4_TAG": 0.0, "Pos_2:Pos_3:Pos_4_CCA": 0.0, "Pos_0:Pos_3:Pos_5_CTG": 0.0, "Pos_1:Pos_2_TG": 0.04390068153311543, "Pos_2:Pos_3:Pos_5_GAG": 0.0, "Pos_1:Pos_2:Pos_5_AAT": 0.0, "Pos_2:Pos_3:Pos_4_GCT": 0.0, "Pos_0:Pos_1:Pos_4_TTC": 0.0, "Pos_0:Pos_1:Pos_2_TTA": 0.0, "Pos_0:Pos_1:Pos_4_ACC": 0.0, "Pos_1:Pos_3:Pos_5_CCG": 0.0, "Pos_0:Pos_1:Pos_5_CCA": 0.0, "Pos_1:Pos_3:Pos_5_GAG": 0.0, "Pos_1:Pos_3_AG": 0.0, "Pos_1:Pos_3:Pos_5_GCC": 0.0, "Pos_0:Pos_1:Pos_2_ATG": 0.0, "Pos_1:Pos_3:Pos_5_AGC": -0.04300742320162679, "Pos_0:Pos_1:Pos_2_ATT": 0.0, "Pos_1:Pos_2:Pos_4_GTC": 0.0, "Pos_2:Pos_4:Pos_5_TAT": 0.0, "Pos_0:Pos_4:Pos_5_GAC": 0.0, "Pos_1:Pos_5_CA": 0.003298623030101707, "Pos_0:Pos_3:Pos_5_TCC": 0.0, "Pos_1:Pos_2:Pos_5_TGG": 0.0, "Pos_0:Pos_2:Pos_4_CCA": 0.0, "Pos_0:Pos_3:Pos_4_ACC": 0.0, "Pos_1:Pos_2:Pos_5_AAA": 0.0, "Pos_1:Pos_3:Pos_4_TCT": 0.013952208866666626, "Pos_0:Pos_3:Pos_5_AAC": 0.09143720497694893, "Pos_0:Pos_3:Pos_5_ATC": 0.0, "Pos_1:Pos_5_AT": 0.0, "Pos_0:Pos_2:Pos_5_AGG": 0.0, "Pos_0:Pos_2:Pos_5_TGG": 0.041148258689187645, "Pos_0:Pos_3:Pos_4_ATC": 0.0, "Pos_1:Pos_2:Pos_3_CAT": 0.0, "Pos_0:Pos_3_GA": 0.0, "Pos_0:Pos_1:Pos_4_AAT": 0.09806048724891926, "Pos_2:Pos_3:Pos_4_ACG": 0.0, "Pos_1:Pos_2:Pos_3_GAA": 0.0, "Pos_1:Pos_4:Pos_5_ACA": 0.0, "Pos_1:Pos_3:Pos_5_TCA": 0.0, "Pos_0:Pos_1:Pos_4_ACT": 0.04852591163083723, "Pos_2:Pos_3:Pos_4_CAT": 0.0, "Pos_2:Pos_3:Pos_5_GGT": 0.0, "Pos_0:Pos_2:Pos_5_GGC": 0.0, "Pos_4:Pos_5_AC": 0.0, "Pos_0:Pos_2:Pos_3_CAG": 0.0, "Pos_0:Pos_1:Pos_3_TAA": 0.0, "Pos_2:Pos_4:Pos_5_ACG": 0.19139165061160912, "Pos_0:Pos_1:Pos_3_GTA": 0.0, "Pos_0:Pos_1:Pos_3_TAG": 0.0, "Pos_1:Pos_5_CG": -0.037592761175851884, "Pos_1:Pos_4:Pos_5_TGT": 0.0, "AtoC": -0.1503411426946532, "Pos_0:Pos_1:Pos_5_CAA": 0.0, "Pos_1:Pos_2:Pos_4_TAC": 0.0, "Pos_1:Pos_2:Pos_3_TAG": -0.11752842697643177, "Pos_0:Pos_3:Pos_4_TTT": 0.0, "Pos_1:Pos_2:Pos_5_CAA": 0.0, "Pos_2:Pos_3:Pos_4_CTG": 0.0, "Pos_0:Pos_1:Pos_2_GGA": 0.0, "Pos_2:Pos_3:Pos_5_CGT": 0.0, "Pos_0:Pos_3:Pos_5_CGT": 0.0, "Pos_0:Pos_1:Pos_5_TGC": 0.0, "Pos_1:Pos_3:Pos_5_AAC": 0.0, "Pos_1:Pos_3:Pos_5_CGC": 0.0, "Pos_1:Pos_3:Pos_5_CTA": 0.0, "Pos_5_A": 0.04914116411698568, "Pos_1:Pos_4:Pos_5_GCA": 0.0, "Pos_0:Pos_2_AT": 0.0, "Pos_0:Pos_2:Pos_4_AAC": 0.0, "Pos_1:Pos_3:Pos_5_AGG": -0.05138854333893773, "Pos_1:Pos_4:Pos_5_TTT": 0.0, "Pos_0:Pos_2:Pos_4_ACT": 0.0, "Pos_1:Pos_2:Pos_3_CTA": 0.0, "Pos_1:Pos_5_TG": 0.0, "Pos_1:Pos_4:Pos_5_CCT": -0.05729311883853038, "Pos_1:Pos_2:Pos_4_TTC": 0.00415154811163906, "Pos_2:Pos_3:Pos_5_CTA": 0.036797811706694154, "Pos_0:Pos_2:Pos_3_ATT": 0.0, "Pos_2:Pos_4:Pos_5_AGC": 0.0, "Pos_0:Pos_1:Pos_3_TTT": 0.0, "Pos_1:Pos_2:Pos_3_GTC": 0.0, "Pos_0:Pos_5_GT": 0.0, "Pos_1:Pos_2:Pos_4_TTA": 0.0, "Pos_1:Pos_3:Pos_5_ACG": 0.0, "Pos_1:Pos_4_CT": 0.0, "Pos_2:Pos_3:Pos_5_GAT": 0.0015454920739050373, "Pos_0:Pos_1:Pos_4_CCC": 0.0, "Pos_0:Pos_4:Pos_5_ACC": 0.0, "Pos_1:Pos_2:Pos_4_CCC": -0.03393134373253361, "Pos_0:Pos_4:Pos_5_GGG": 0.0, "Pos_0_A": 0.0, "Pos_2:Pos_3_CG": -0.06124724880659827, "Pos_0:Pos_4:Pos_5_GGT": 0.0, "Pos_1:Pos_3:Pos_4_GGA": 0.0, "Pos_1:Pos_3:Pos_5_GCT": 0.0, "Pos_0:Pos_2:Pos_4_TCA": 0.0, "Pos_0:Pos_2_TA": 0.0, "Pos_0:Pos_1:Pos_2_GAC": -0.02834925517725526, "Pos_0:Pos_2:Pos_4_TAC": 0.0, "Pos_0:Pos_1:Pos_5_GAG": 0.0, "Pos_0:Pos_3_TA": 0.0, "Pos_0:Pos_3_AT": 0.001048249855406106, "Pos_0:Pos_3:Pos_5_CAG": 0.0, "Pos_1:Pos_2:Pos_5_TGC": 0.0663872924166095, "Pos_0:Pos_4:Pos_5_TTC": 0.061317710602051025, "Pos_1:Pos_2:Pos_5_CGT": 0.0, "Pos_1:Pos_3:Pos_4_GCT": 0.0, "Pos_0:Pos_4:Pos_5_CCA": 0.0, "Pos_0:Pos_3:Pos_4_CGG": 0.0, "Pos_1:Pos_3:Pos_4_AAC": 0.0, "Pos_1:Pos_2:Pos_4_GCC": 0.0, "Pos_0:Pos_3:Pos_5_TTT": 0.0, "Pos_4:Pos_5_TA": 0.0, "Pos_1:Pos_2:Pos_5_TAG": 0.05609950903974803, "Pos_0:Pos_1:Pos_3_AGC": -0.0010095678981103945, "Pos_3:Pos_4:Pos_5_TTA": -0.05848434771080326, "Pos_3:Pos_4_GA": -0.08640912435439507, "Pos_0:Pos_4_GC": 0.0, "Pos_0:Pos_1:Pos_5_TAC": 0.0, "Pos_0:Pos_3:Pos_4_GGA": 0.0, "Pos_0:Pos_4:Pos_5_CTT": 0.0, "Pos_3:Pos_4:Pos_5_GGT": 0.0, "Pos_0:Pos_3:Pos_5_CTC": 0.0, "Pos_1:Pos_2:Pos_3_CCC": 0.0, "Pos_0:Pos_2:Pos_5_TCC": 0.0, "Pos_0:Pos_3:Pos_5_CGC": 0.0, "Pos_1:Pos_4:Pos_5_AGG": 0.0, "Pos_0:Pos_3:Pos_4_TCA": 0.0, "Pos_2:Pos_3:Pos_5_CCA": 0.0, "Pos_0:Pos_4_CG": 0.0, "Pos_1:Pos_2:Pos_4_ATT": 0.008223830374098687, "Pos_0:Pos_2:Pos_3_TGT": 0.0, "Pos_2:Pos_5_CC": -0.0032207938544010634, "Pos_0:Pos_2:Pos_5_CAG": 0.0836630719832257, "Pos_1:Pos_2:Pos_5_ATC": 0.0, "Pos_0:Pos_3_AC": 0.0, "Pos_0:Pos_1:Pos_3_ATC": 0.0, "Pos_1:Pos_5_GG": 0.0, "Pos_0:Pos_4:Pos_5_TCA": 0.0, "Pos_1:Pos_3:Pos_5_GAC": 0.0, "Pos_2:Pos_3:Pos_4_TAT": 0.0, "Pos_1:Pos_2:Pos_3_ATG": 0.0, "Pos_1:Pos_2:Pos_5_ATG": 0.0, "Pos_0:Pos_4_TT": 0.0, "Pos_0:Pos_4:Pos_5_TTT": 0.0, "Pos_1:Pos_4:Pos_5_GTG": 0.0, "Pos_0:Pos_2:Pos_4_GTT": 0.0, "Pos_1:Pos_3:Pos_4_GAG": 0.001574654421785108, "Pos_1:Pos_2:Pos_4_TAT": 0.0, "Pos_0:Pos_3:Pos_4_CGC": 0.0, "Pos_0:Pos_2_TC": 0.0, "Pos_3:Pos_4:Pos_5_CGC": 0.0, "Pos_0:Pos_3:Pos_4_CTA": 0.0, "Pos_0:Pos_2:Pos_5_TAG": 0.0, "Pos_3:Pos_4:Pos_5_TCG": 0.0, "Pos_0:Pos_4:Pos_5_ACG": 0.0, "Pos_2:Pos_3:Pos_4_TTT": 0.0, "Pos_2:Pos_5_TT": 0.0, "Pos_2:Pos_3:Pos_4_AGC": 0.0, "Pos_1:Pos_2:Pos_3_TAC": 0.0, "Pos_4:Pos_5_GA": 0.0, "Pos_0:Pos_3:Pos_4_AAG": 0.0, "Pos_0:Pos_3:Pos_5_TAT": 0.0, "Pos_0:Pos_4:Pos_5_TAC": 0.0, "Pos_1:Pos_4_CA": 0.0, "Pos_0:Pos_4:Pos_5_AGT": 0.0, "Pos_1:Pos_3:Pos_5_CCA": 0.0, "Pos_1:Pos_2:Pos_4_GGA": 0.0, "Pos_1:Pos_2:Pos_5_GGT": 0.0, "Pos_1:Pos_2:Pos_5_TAA": 0.0, "Pos_0:Pos_4:Pos_5_ATA": 0.0, "Pos_3:Pos_4:Pos_5_GAT": 0.0, "Pos_1:Pos_4:Pos_5_GCT": 0.0, "Pos_1:Pos_4:Pos_5_CGA": 0.0, "Pos_0:Pos_1:Pos_3_TAT": 0.06317097343291203, "Pos_1:Pos_2:Pos_4_TGA": 0.0, "Pos_2:Pos_4:Pos_5_GAC": 0.026348465987259782, "Pos_1:Pos_4:Pos_5_TCC": 0.0, "Pos_2:Pos_3:Pos_4_GTT": 0.0, "Pos_1:Pos_4:Pos_5_TAG": 0.0, "Pos_1:Pos_3:Pos_5_CAA": 0.0, "Pos_1:Pos_2:Pos_5_TTA": 0.0, "Pos_0:Pos_1:Pos_3_GAT": 0.05692807619578203, "Pos_0:Pos_1:Pos_3_TCC": 0.0698629293109263, "Pos_1:Pos_2:Pos_5_CAG": 0.0, "Pos_0:Pos_3:Pos_4_GCT": 0.0, "Pos_3:Pos_4:Pos_5_ACG": 0.0, "Pos_2:Pos_4_AG": 0.0, "Pos_0:Pos_2:Pos_4_GTG": 0.0, "Pos_0:Pos_2:Pos_4_TAG": 0.0, "Pos_1:Pos_2_AG": 0.09574476724736283, "Pos_1:Pos_3:Pos_4_TAC": -0.006562596589037586, "Pos_1:Pos_3:Pos_4_AGC": 0.01026840989771504, "Pos_0:Pos_3:Pos_4_ACT": 0.0, "Pos_0:Pos_1:Pos_3_TGT": -0.09049841377524381, "Pos_3:Pos_4_GC": 0.0, "Pos_3:Pos_4:Pos_5_TAC": 0.0, "Pos_0:Pos_2:Pos_3_GTG": 0.11666696919783681, "Pos_1:Pos_4:Pos_5_TCA": 0.0, "Pos_0:Pos_1:Pos_2_GAT": 0.0, "Pos_0:Pos_1:Pos_2_TAT": 0.0, "Pos_1:Pos_2:Pos_3_GCC": 0.0, "Pos_2:Pos_4:Pos_5_TTC": 0.0, "Pos_3:Pos_4:Pos_5_CGA": 0.0, "Pos_2:Pos_3:Pos_4_CGC": -0.027755080595008003, "Pos_2:Pos_3:Pos_5_TTT": -0.026043727830307662, "Pos_3:Pos_4:Pos_5_TGA": 0.11001182917758286, "Pos_0:Pos_1:Pos_2_TCC": 0.0, "Pos_2:Pos_3:Pos_5_ACA": 0.0, "Pos_4:Pos_5_AA": 0.061921643247035085, "Pos_1:Pos_4:Pos_5_TGA": -0.00567081939176791, "Pos_2_C": -0.10664174237189662, "Pos_0:Pos_1:Pos_4_AGC": 0.025183453812317496, "Pos_0:Pos_3_CT": 0.0, "Pos_2:Pos_3:Pos_5_GTA": 0.0, "Pos_2:Pos_3:Pos_5_CAG": 0.1443572739745401, "Pos_0:Pos_2:Pos_4_TCG": 0.0, "Pos_0:Pos_3:Pos_5_TGG": 0.0, "Pos_3:Pos_4:Pos_5_GAA": 0.0, "Pos_1:Pos_4:Pos_5_TTG": 0.0, "Pos_1:Pos_5_TC": 0.0, "Pos_1:Pos_4:Pos_5_TAT": 0.0, "Pos_0:Pos_2:Pos_3_CCA": 0.0, "Pos_2:Pos_3:Pos_4_ATA": -0.10110707418693922, "Pos_1:Pos_2:Pos_3_GGG": 0.0, "Pos_0:Pos_2:Pos_4_GAA": 0.0, "Pos_1:Pos_2:Pos_4_CAA": 0.0, "Pos_1:Pos_3_CC": 0.0, "Pos_3:Pos_4:Pos_5_CCG": 0.0, "Pos_1:Pos_4:Pos_5_CTA": -0.16397432643049628, "Pos_0:Pos_4:Pos_5_CGT": 0.0, "Pos_2:Pos_3:Pos_4_GCG": 0.0, "Pos_1:Pos_2:Pos_5_GAA": 0.0, "Pos_3:Pos_5_AT": 0.0, "Pos_1:Pos_3:Pos_4_TAT": 0.0, "Pos_2:Pos_3:Pos_5_CAA": 0.0, "Pos_0:Pos_3_TC": 0.0, "Pos_1:Pos_2:Pos_5_ACT": -0.09540709575978394, "Pos_0:Pos_3:Pos_5_CCT": 0.0, "Pos_0:Pos_3:Pos_5_TGT": 0.0, "Pos_2:Pos_4_TC": 0.0, "Pos_0:Pos_2:Pos_3_AGT": -0.09160671151924779, "Pos_5_C": 0.0, "Pos_0:Pos_2_AC": 0.0, "Pos_1:Pos_3:Pos_4_ATT": 0.1753331447335394, "Pos_2:Pos_4:Pos_5_TCG": 0.0, "Pos_3:Pos_4_TG": 0.0, "Pos_0:Pos_1:Pos_4_TCC": 0.0, "Pos_1:Pos_2:Pos_5_AAC": -0.005383265037982512, "Pos_1:Pos_2:Pos_3_CCG": 0.0, "Pos_0:Pos_2:Pos_3_GCT": 0.0, "Pos_1:Pos_3:Pos_5_AAA": 0.0, "Pos_2:Pos_4_AT": 0.04793700279084229, "Pos_0:Pos_1:Pos_4_GTA": 0.0, "Pos_3:Pos_4:Pos_5_CCT": 0.0, "Pos_0:Pos_2:Pos_3_ACT": 0.0, "Pos_0:Pos_1:Pos_5_CAT": -0.11759313394062205, "Pos_1:Pos_2:Pos_5_TTT": 0.0, "Pos_0:Pos_2:Pos_4_TTT": 0.0, "Pos_1:Pos_2:Pos_5_GCG": 0.0, "Pos_1:Pos_2:Pos_3_CAC": 0.0, "Pos_0:Pos_3:Pos_5_GTG": 0.022210888612673084, "Pos_0:Pos_2:Pos_3_AAT": 0.034489552746707314, "Pos_0:Pos_4:Pos_5_CAT": -0.018236444507746096, "Pos_0:Pos_2:Pos_3_GAG": 0.04910636466785864, "Pos_0:Pos_3:Pos_4_AGC": 0.0, "Pos_0:Pos_4_AG": 0.0, "Pos_1:Pos_3_CG": 0.0, "Pos_3:Pos_4:Pos_5_GGA": -0.007370397530755842, "Pos_2:Pos_3:Pos_4_CGT": 0.0, "Pos_0:Pos_4_GG": 0.0, "Pos_0:Pos_1:Pos_4_TTG": 0.0, "Pos_1:Pos_3:Pos_4_CAG": 0.0, "Pos_0:Pos_3:Pos_5_ACT": 0.0073890272103062865, "Pos_0:Pos_2:Pos_3_TGC": 0.0, "Pos_0:Pos_4:Pos_5_TCC": 0.0, "Pos_0:Pos_2:Pos_3_GAC": 0.0, "Pos_0:Pos_3:Pos_5_GGA": 0.0, "Pos_0:Pos_3_TG": -0.0059955785468245315, "Pos_0:Pos_1:Pos_5_TCA": 0.0, "Pos_0:Pos_4:Pos_5_ACT": 0.0, "GtoA": -0.5091547364471133, "Pos_2_A": 0.0, "Pos_4_T": 0.0, "Pos_2:Pos_4_CA": 0.0, "Pos_1:Pos_4:Pos_5_ATT": 0.0, "Pos_3:Pos_4_TA": 0.0, "Pos_0:Pos_1:Pos_5_CGA": 0.0, "Pos_1:Pos_3:Pos_4_TAG": 0.0, "Pos_3:Pos_5_CC": 0.0, "Pos_0:Pos_1_AA": 0.0, "Pos_0:Pos_1:Pos_3_GTC": 0.06986077320326216, "Pos_3_G": -0.03173985897146354, "Pos_0:Pos_5_CC": 0.0, "Pos_1:Pos_4_CC": -0.004466511813438466, "Pos_1:Pos_5_GA": 0.0, "Pos_1:Pos_2:Pos_4_ATG": 0.0, "Pos_1:Pos_4_AG": -0.04318796226768851, "Pos_0:Pos_1:Pos_2_CTC": -0.016170492065048673, "Pos_1:Pos_3:Pos_5_AGT": 0.14713671349998836, "Pos_1:Pos_2:Pos_4_CGA": 0.0, "Pos_1:Pos_2:Pos_4_TGG": 0.0, "Pos_1:Pos_3:Pos_4_ATC": 0.0, "Pos_1:Pos_2:Pos_5_TCC": 0.0, "Pos_0:Pos_2:Pos_3_GGC": 0.0, "Pos_0:Pos_4:Pos_5_AAT": 0.0, "Pos_0:Pos_2:Pos_5_TTA": 0.0, "Pos_1:Pos_3:Pos_4_TTG": 0.0, "Pos_0:Pos_1:Pos_2_TAA": -0.04518123481781571, "Pos_0:Pos_4_CC": 0.0, "Pos_3:Pos_5_AC": 0.0, "Pos_0:Pos_2:Pos_3_TAA": 0.0, "Pos_0:Pos_1:Pos_4_GTC": 0.0, "Pos_0:Pos_2:Pos_5_ACC": 0.0, "Pos_4:Pos_5_TG": 0.0, "Pos_2:Pos_3:Pos_4_AAT": -0.17043019346259922, "Pos_0:Pos_1:Pos_4_AAA": 0.0, "Pos_0:Pos_1_CA": 0.0, "Pos_1:Pos_2:Pos_3_GTA": 0.0, "Pos_0:Pos_1_AC": 0.0, "Pos_0:Pos_1:Pos_4_GCT": -0.025205603221082583, "Pos_0:Pos_3:Pos_5_GGG": 0.0, "Pos_0:Pos_3:Pos_5_ACG": 0.0, "Pos_0:Pos_2:Pos_5_CTA": 0.0, "Pos_0:Pos_1_CC": 0.0, "Pos_0:Pos_4:Pos_5_GCG": 0.0, "Pos_1:Pos_2:Pos_3_ACG": 0.0, "Pos_0:Pos_1:Pos_3_GAG": -0.07784759006312272, "Pos_1:Pos_2:Pos_5_CTG": 0.0, "Pos_1:Pos_5_AC": 0.0, "Pos_3:Pos_5_GC": 0.0, "Pos_2:Pos_3:Pos_4_ACA": 0.0, "Pos_2:Pos_4_AC": 0.0, "Pos_1:Pos_2_TC": 0.0, "Pos_2:Pos_3:Pos_4_GAG": 0.0, "Pos_1:Pos_2:Pos_3_TCT": 0.0, "Pos_5_G": 0.0, "Pos_0:Pos_2:Pos_4_TTC": -0.11402440030409448, "Pos_3:Pos_4:Pos_5_TCC": 0.09351310135333268, "Pos_0:Pos_3:Pos_4_TTA": 0.008897259903649861, "Pos_0:Pos_1:Pos_5_TGG": 0.05052245773812122, "Pos_4:Pos_5_CT": 0.0, "Pos_1:Pos_3:Pos_5_CGG": 0.0, "Pos_3:Pos_5_TA": 0.01685893448079771, "Pos_2:Pos_3_AT": 0.0, "Pos_2:Pos_3:Pos_4_GCA": 0.04904864068263611, "Pos_0:Pos_1:Pos_5_AAG": 0.0, "Pos_0:Pos_1:Pos_5_CAC": 0.0, "Pos_3:Pos_4:Pos_5_AGG": 0.0, "Pos_1:Pos_2:Pos_4_CCT": 0.09164287749068459, "Pos_0:Pos_3:Pos_5_GCG": 0.0, "Pos_1:Pos_4:Pos_5_GTC": 0.0, "Pos_3:Pos_4:Pos_5_TAT": -0.14855955518699196, "Pos_0:Pos_1:Pos_5_AAC": 0.0, "Pos_1:Pos_3:Pos_5_TTT": 0.12365279241906489, "Pos_0:Pos_1:Pos_4_TAC": 0.0, "Pos_1:Pos_3:Pos_4_GAT": 0.0, "Pos_0:Pos_2:Pos_4_GCC": 0.0, "Pos_0:Pos_3:Pos_4_GAC": 0.0, "Pos_0:Pos_1:Pos_2_GTT": 0.0, "Pos_2:Pos_3:Pos_5_CTT": 0.0, "Pos_1:Pos_4:Pos_5_TAA": 0.0, "CtoT": -0.5180111208982364, "Pos_1:Pos_3:Pos_4_CAT": 0.0, "Pos_0:Pos_2:Pos_5_AAC": 0.0, "Pos_0:Pos_2:Pos_5_ATT": 0.0, "Pos_0:Pos_1:Pos_3_CGA": 0.0, "Pos_2:Pos_4:Pos_5_GCT": 0.019308053965478317, "Pos_0:Pos_4:Pos_5_GCC": 0.0, "Pos_0:Pos_2:Pos_5_CCA": 0.0, "Pos_2:Pos_4:Pos_5_CGG": 0.0, "Pos_2:Pos_3:Pos_4_GGA": -0.09748999376939475, "Pos_0:Pos_1:Pos_4_GCG": 0.0, "Pos_0:Pos_1:Pos_3_AAG": 0.15718934953970787, "Pos_0:Pos_4:Pos_5_TGG": 0.0, "Pos_1:Pos_4:Pos_5_CCC": 0.0, "Pos_1:Pos_2:Pos_3_GTG": -0.0593224228958971, "Pos_0:Pos_1:Pos_4_CAT": 0.0, "Pos_1_T": 0.10434177910432273, "Pos_0:Pos_1:Pos_4_TCA": 0.0, "Pos_2:Pos_4:Pos_5_AGT": 0.0, "Pos_1:Pos_2:Pos_4_GTA": 0.0, "Pos_3:Pos_4:Pos_5_TCT": 0.0, "Pos_0:Pos_1:Pos_4_CGG": 0.08362399760329987, "Pos_3:Pos_4_AT": -0.05305685810328608, "Pos_3:Pos_4_AG": 0.13378544806896506, "Pos_1:Pos_3:Pos_4_GGG": 0.0, "Pos_2:Pos_4:Pos_5_CGC": 0.0, "Pos_1:Pos_3:Pos_4_GTC": 0.07876771456709197, "Pos_1:Pos_3:Pos_4_TGC": 0.0, "Pos_3:Pos_4:Pos_5_GGG": 0.04262317948773904, "Pos_1:Pos_3:Pos_4_AGT": 0.0, "Pos_0:Pos_3:Pos_5_ACA": 0.0, "Pos_2:Pos_4:Pos_5_GTG": 0.0, "Pos_1:Pos_4_AT": 0.0, "Pos_3:Pos_4:Pos_5_GGC": 0.0, "Pos_2:Pos_5_AT": 0.0, "Pos_0:Pos_1:Pos_4_CGA": 0.0, "Pos_0:Pos_1:Pos_3_ACG": 0.0, "Pos_2:Pos_3:Pos_5_AGA": 0.0, "Pos_1:Pos_2:Pos_5_GTT": 0.0, "Pos_3:Pos_4:Pos_5_AAT": 0.0, "Pos_2:Pos_3:Pos_5_ATT": 0.0, "Pos_0:Pos_1:Pos_5_GCA": 0.0, "Pos_2:Pos_4:Pos_5_ACC": 0.0, "Pos_0:Pos_1:Pos_2_GCA": 0.0, "Pos_2:Pos_3:Pos_4_CAA": 0.0, "Pos_0:Pos_3:Pos_5_AGT": 0.0, "Pos_0:Pos_2:Pos_5_GCA": 0.0, "GtoT": 0.13825122239269746, "Pos_2:Pos_4:Pos_5_ACA": 0.0, "Pos_2:Pos_3:Pos_5_ACG": 0.0, "Pos_2:Pos_3:Pos_5_CTG": 0.0, "Pos_3:Pos_4:Pos_5_ACT": 0.0, "Pos_0:Pos_3:Pos_5_GTC": -0.02004023387651434, "Pos_0:Pos_1:Pos_4_ATG": 0.0, "Pos_0:Pos_3:Pos_5_CAT": 0.0, "Pos_1:Pos_2:Pos_5_TGT": 0.0, "Pos_0:Pos_2:Pos_4_GCA": 0.0018219783530565698, "Pos_0:Pos_1:Pos_3_ATG": 0.0, "Pos_1:Pos_2:Pos_4_TGC": 0.0, "Pos_0:Pos_2:Pos_4_GAC": 0.0, "Pos_0:Pos_1:Pos_5_GGT": 0.0, "Pos_2:Pos_3:Pos_5_TGC": 0.0, "Pos_1:Pos_3:Pos_4_AGA": 0.0, "Pos_0:Pos_2:Pos_4_CCT": 0.0, "TtoA": 0.971269845381364, "Pos_1:Pos_3_AT": 0.0, "Pos_0:Pos_1:Pos_5_AGG": 0.0, "Pos_1:Pos_2:Pos_3_TGT": -0.01971783660576813, "Pos_1:Pos_2:Pos_3_CCA": 0.0, "Pos_0:Pos_1:Pos_2_CCA": 0.0, "Pos_0:Pos_3:Pos_4_AAA": 0.0, "Pos_4:Pos_5_TT": 0.05081272505075554, "Pos_3:Pos_4_CG": -0.08303604285523047, "Pos_0:Pos_3:Pos_5_GCT": 0.0, "Pos_2:Pos_4:Pos_5_TCT": -0.06847281308870848, "Pos_1:Pos_4:Pos_5_TGG": 0.0, "Pos_1:Pos_4:Pos_5_TCT": 0.0, "Pos_0:Pos_2:Pos_5_GTC": 0.0, "Pos_2:Pos_3:Pos_4_TCG": -0.2281274922326934, "Pos_0:Pos_2:Pos_5_GTT": -0.1878178376908352, "Pos_2:Pos_3_CT": 0.10420771131770036, "Pos_0:Pos_2:Pos_5_TGA": 0.0, "Pos_0:Pos_4:Pos_5_CAG": -0.06985046122982955, "Pos_3:Pos_4:Pos_5_CTG": 0.0, "Pos_1:Pos_3:Pos_5_CGA": 0.2059440855793363, "Pos_1:Pos_5_AG": 0.0, "Pos_2:Pos_4:Pos_5_TCC": 0.0, "Pos_1:Pos_2:Pos_4_ACC": 0.04500510755553985, "Pos_0:Pos_3:Pos_4_CGA": 0.0, "Pos_0:Pos_2_CT": -0.014992218245152374, "Pos_0:Pos_1:Pos_5_TCG": 0.0, "Pos_0:Pos_3:Pos_5_TCT": 0.0, "Pos_1:Pos_2:Pos_3_AGC": 0.0, "Pos_1:Pos_3:Pos_5_ATA": 0.0, "Pos_0:Pos_4:Pos_5_ATT": 0.0016472418355796626, "Pos_0_G": -0.02204615606258577, "Pos_4:Pos_5_TC": 0.0, "Pos_0:Pos_3:Pos_4_GAG": 0.0, "Pos_2:Pos_3:Pos_4_GTC": 0.08093014988662313, "Pos_0:Pos_1:Pos_4_TGG": 0.0, "Pos_0:Pos_1:Pos_3_TCG": 0.0, "Pos_1:Pos_3:Pos_4_TTA": 0.0, "Pos_3:Pos_4:Pos_5_GTC": 0.0, "Pos_0:Pos_1:Pos_5_CGG": -0.02192370740974847, "CtoG": -1.9971339220929043, "Pos_3:Pos_5_GT": 0.0, "Pos_0:Pos_1_TA": 0.0, "Pos_0:Pos_1:Pos_2_TTT": 0.0, "Pos_2:Pos_3:Pos_5_TCA": -0.16646522128670777, "Pos_1:Pos_3:Pos_4_CAA": 0.0, "Pos_1:Pos_3:Pos_4_GCA": 0.0019947078723117125, "Pos_0:Pos_1:Pos_2_TAC": 0.0, "Pos_0:Pos_1:Pos_3_CGT": 0.030927204971357185, "Pos_0:Pos_1:Pos_5_AAT": 0.08826266877178315, "Pos_1:Pos_3_CA": 0.0, "Pos_1:Pos_5_CC": 0.0, "Pos_2:Pos_3:Pos_5_CAT": -0.09846248697980683, "Pos_0:Pos_2:Pos_5_TTG": 0.0, "Pos_0:Pos_1:Pos_2_GGG": 0.0, "Pos_0:Pos_3:Pos_4_CTG": 0.0, "Pos_2:Pos_3_GA": 0.0, "Pos_2:Pos_3:Pos_4_AGT": 0.010197170536416712, "Pos_1:Pos_2:Pos_3_AGG": 0.0, "Pos_0:Pos_2:Pos_3_AGG": 0.0, "Pos_0:Pos_4:Pos_5_ACA": 0.0, "Pos_0:Pos_1_TC": 0.03553243648962581, "Pos_1:Pos_4:Pos_5_AAC": 0.0, "Pos_2:Pos_4:Pos_5_CCT": 0.09823168326793745, "Pos_3:Pos_4:Pos_5_ATA": 0.0, "Pos_2:Pos_3:Pos_4_CGG": 0.0, "Pos_4:Pos_5_GT": 0.0, "Pos_0:Pos_1:Pos_3_GCT": 0.0, "Pos_0:Pos_4_AA": 0.0, "Pos_0:Pos_2:Pos_4_GTA": 0.0, "Pos_2:Pos_5_GA": 0.0, "Pos_2:Pos_4:Pos_5_GTA": 0.0036346116846837266, "Pos_0:Pos_2:Pos_3_GCA": 0.0, "Pos_0:Pos_1:Pos_4_AGA": -0.12662832464121782, "Pos_1:Pos_2:Pos_3_GAT": -0.15924749621753503, "Pos_1:Pos_2:Pos_5_AGC": 0.0, "Pos_1:Pos_4:Pos_5_ATG": 0.0, "Pos_3:Pos_4:Pos_5_TAG": 0.13519745132790859, "Pos_0:Pos_2:Pos_5_CAA": 0.0, "Pos_1:Pos_2:Pos_4_AAC": 0.0, "Pos_0:Pos_3:Pos_4_GCC": 0.0, "Pos_2:Pos_4:Pos_5_CCC": -0.09847166071757119, "Pos_0:Pos_3:Pos_5_CAA": 0.0, "Pos_0:Pos_1:Pos_3_CAA": 0.0, "Pos_2:Pos_4:Pos_5_GTC": 0.0, "Pos_2:Pos_3:Pos_5_AAC": 0.034031107625225286, "Pos_0:Pos_2:Pos_3_TGG": 0.0, "Pos_0:Pos_2:Pos_5_TTC": 0.0, "Pos_2:Pos_3_GT": 0.0, "Pos_0:Pos_1:Pos_5_TTA": 0.0, "Pos_0:Pos_2:Pos_3_TAG": 0.0, "Pos_1:Pos_3:Pos_4_TCG": -0.00870979742936672, "Pos_1:Pos_2:Pos_3_TGA": 0.0, "Pos_0:Pos_1:Pos_2_AGC": -0.08100554356657372, "Pos_0:Pos_2:Pos_5_AGT": 0.0, "Pos_1:Pos_2:Pos_3_AAT": 0.0, "Pos_0:Pos_3:Pos_4_TTC": 0.0, "Pos_3:Pos_4_GG": 0.0, "Pos_1:Pos_3:Pos_5_ATT": 0.0, "Pos_0:Pos_2:Pos_4_GCG": 0.0, "Pos_0:Pos_3:Pos_4_TGA": 0.0, "Pos_0:Pos_2:Pos_3_TAT": 0.03778855372840789, "Pos_1:Pos_4_GC": 0.0, "Pos_2:Pos_4_CT": -0.13969493348325754, "Pos_1:Pos_3:Pos_4_GTA": 0.0, "Pos_0:Pos_2:Pos_5_CCG": 0.08030522977829084, "Pos_2:Pos_3:Pos_4_TTG": 0.0, "Pos_2:Pos_3:Pos_4_CCG": 0.0, "Pos_0:Pos_4:Pos_5_CTA": 0.0, "Pos_0:Pos_3:Pos_4_TAT": 0.0, "Pos_2:Pos_4:Pos_5_GAT": 0.0, "Pos_1:Pos_2:Pos_5_ATT": 0.05825483357581579, "Pos_0:Pos_2:Pos_4_CAA": 0.07640819471397636, "Pos_2:Pos_3:Pos_4_CTT": 0.0, "Pos_0:Pos_5_TA": 0.0, "Pos_2:Pos_4:Pos_5_GGC": 0.0, "Pos_3:Pos_4:Pos_5_TTC": 0.05605545720987242, "Pos_1:Pos_4:Pos_5_AAG": 0.0, "Pos_1:Pos_4:Pos_5_AGA": 0.0, "Pos_2:Pos_3:Pos_5_GTT": 0.0, "Pos_0:Pos_1:Pos_3_ACA": 0.0, "Pos_0:Pos_1:Pos_4_TGA": 0.051746122675460096, "Pos_2:Pos_4:Pos_5_ATT": 0.048793871663146964, "Pos_0:Pos_1:Pos_2_CCG": 0.0, "Pos_1:Pos_2:Pos_4_AGA": 0.0, "Pos_2:Pos_3:Pos_5_TCT": 0.0, "Pos_0:Pos_3:Pos_5_TTC": 0.015699062888321437, "Pos_0:Pos_2:Pos_3_GGT": 0.0, "Pos_0:Pos_2:Pos_5_GAC": 0.0, "Pos_4:Pos_5_CC": -0.044306250883217206, "Pos_3:Pos_4:Pos_5_GCC": 0.0, "Pos_1:Pos_3_GT": 0.0, "Pos_1:Pos_4_AC": 0.0, "Pos_0:Pos_2:Pos_4_ATC": 0.0, "Pos_0:Pos_4:Pos_5_TCT": 0.0, "Pos_3:Pos_4:Pos_5_CAG": 0.0, "Pos_2:Pos_5_TG": 0.0, "Pos_1:Pos_2:Pos_4_GGG": 0.0, "Pos_0:Pos_2:Pos_5_AAG": -0.04442306562024141, "Pos_2:Pos_3:Pos_5_GAA": 0.0, "Pos_3:Pos_4:Pos_5_ATG": 0.0, "Pos_0:Pos_3:Pos_4_TGG": 0.0, "Pos_0:Pos_1:Pos_5_AGT": -0.013614043156369724, "Pos_0:Pos_1:Pos_3_ACC": 0.0, "Pos_0:Pos_2_TG": 0.0, "Pos_1:Pos_3:Pos_5_CCC": 0.0, "Pos_0:Pos_2:Pos_5_TAT": 0.0, "Pos_1:Pos_2:Pos_5_CTC": 0.0, "Pos_2:Pos_4:Pos_5_CAC": 0.0, "Pos_2:Pos_4_CC": 0.0, "Pos_0:Pos_1:Pos_2_ACA": 0.0, "Pos_0:Pos_3:Pos_4_CAG": 0.0, "Pos_0:Pos_1:Pos_4_TTT": 0.23822666896104963, "Pos_0:Pos_2:Pos_4_TTG": 0.0, "Pos_0:Pos_2:Pos_4_ACG": -0.13170076840857742, "Pos_1:Pos_2:Pos_5_GAC": 0.0, "Pos_0:Pos_4:Pos_5_GAG": 0.0, "Pos_0:Pos_2:Pos_5_CGT": 0.0, "Pos_0:Pos_1:Pos_5_GGC": 0.0, "Pos_3:Pos_4:Pos_5_CAT": 0.1438528393318981, "Pos_1:Pos_3:Pos_5_TTA": 0.0, "Pos_0:Pos_1:Pos_5_CCG": 0.0, "Pos_1:Pos_2:Pos_5_TAC": 0.0, "Pos_0:Pos_1:Pos_4_GAA": -0.05833974755095986, "Pos_0:Pos_1_AT": 0.0, "Pos_1:Pos_2:Pos_4_ATC": 0.0, "Pos_1:Pos_4:Pos_5_GAA": 0.0, "Pos_0:Pos_4:Pos_5_GCT": 0.0, "Pos_1:Pos_2:Pos_4_ACT": 0.0, "Pos_2:Pos_4:Pos_5_ACT": -0.021196635806075115, "Pos_2:Pos_3:Pos_5_TAA": 0.0, "Pos_0:Pos_4:Pos_5_AGG": 0.0, "Pos_0:Pos_2:Pos_5_AGC": 0.056054316510211956, "Pos_1:Pos_2:Pos_3_TAA": 0.04869924843063919, "Pos_0:Pos_4:Pos_5_AAA": 0.0, "Pos_2:Pos_4:Pos_5_GGG": 0.07588203014834256, "Pos_3:Pos_5_AG": 0.0, "Pos_1:Pos_3:Pos_4_AAT": 0.0, "Pos_0:Pos_1:Pos_5_GAC": 0.0, "Pos_2:Pos_4_CG": 0.0, "Pos_2:Pos_3:Pos_4_TCA": 0.0, "Pos_3:Pos_4_TT": 0.0, "Pos_1:Pos_4:Pos_5_TGC": 0.0, "Pos_0:Pos_1:Pos_5_AGA": 0.08005956659093479, "Pos_0_T": 0.07053621153827515, "Pos_2:Pos_4:Pos_5_GGT": 0.0, "Pos_1_C": 0.0, "Pos_0:Pos_2:Pos_3_CAA": 0.0, "Pos_0:Pos_1:Pos_4_GCA": 0.07263442362359009, "Pos_1:Pos_3:Pos_4_GTG": 0.0, "Pos_1:Pos_2:Pos_3_CGA": -0.24756047130154651, "Pos_0:Pos_3:Pos_5_GCA": 0.0, "Pos_3:Pos_4:Pos_5_GAG": 0.0, "Pos_0:Pos_3:Pos_5_GTT": 0.0, "Pos_2:Pos_3:Pos_4_AAA": 0.0, "Pos_0:Pos_5_GG": 0.0, "Pos_1:Pos_2_CG": -0.14466087709627606, "Pos_1:Pos_3_TA": 0.0, "Pos_2:Pos_5_GC": 0.009011627060750996, "Pos_0:Pos_4:Pos_5_TTG": -0.03638588373767189, "Pos_3_C": 0.10317090655370921, "Pos_0:Pos_3:Pos_5_GCC": 0.0, "Pos_1:Pos_2:Pos_5_CCG": 0.0, "Pos_1:Pos_3_TC": 0.0, "Pos_0:Pos_1:Pos_3_AGT": 0.0, "Pos_1:Pos_2:Pos_4_GCA": 0.0, "Pos_0:Pos_1:Pos_5_ATC": 0.0, "Pos_0:Pos_2:Pos_5_GGG": 0.0, "Pos_0:Pos_2:Pos_4_TAT": 0.04287318797859547, "Pos_0:Pos_1:Pos_4_TAA": 0.0, "Pos_1:Pos_2:Pos_3_CGG": -0.12259626322431061, "Pos_0:Pos_1:Pos_4_TAG": 0.0, "Pos_0:Pos_2:Pos_5_TCG": 0.0, "Pos_3:Pos_4:Pos_5_TGT": 0.0, "Pos_0:Pos_4:Pos_5_CTG": 0.0, "Pos_2:Pos_3_TC": 0.0, "Pos_3:Pos_4:Pos_5_GCT": 0.0, "Pos_3:Pos_4:Pos_5_TAA": 0.011309953936845528, "Pos_0:Pos_1:Pos_2_GCT": 0.0, "Pos_2:Pos_3:Pos_5_AGC": 0.0, "Pos_1:Pos_4:Pos_5_TCG": 0.0, "Pos_0:Pos_2:Pos_3_ATA": 0.0, "Pos_0:Pos_3:Pos_4_CTC": 0.0, "Pos_0:Pos_1:Pos_4_AGG": 0.0, "Pos_1:Pos_3:Pos_4_CGA": 0.0, "Pos_0:Pos_2:Pos_5_TGC": 0.0, "Pos_0:Pos_1_GA": 0.0, "Pos_1:Pos_4_TA": 0.0, "Pos_1:Pos_2:Pos_3_AAC": -0.027615707962783263, "Pos_2:Pos_3:Pos_5_GGA": 0.0, "Pos_4:Pos_5_CG": 0.07402740507748506, "Pos_2:Pos_5_AA": 0.0, "Pos_0:Pos_1:Pos_4_GCC": 0.0, "Pos_0:Pos_1:Pos_2_AAC": 0.0, "Pos_0:Pos_2:Pos_5_GTG": 0.007377762819976186, "Pos_0:Pos_4:Pos_5_TAT": 0.0, "Pos_2:Pos_4:Pos_5_AAA": 0.0, "Pos_0:Pos_4:Pos_5_TGA": 0.0, "Pos_1:Pos_3:Pos_5_TCT": 0.0, "Pos_0:Pos_2:Pos_3_GTT": 0.0, "Pos_2:Pos_4:Pos_5_AAG": 0.0, "Pos_0:Pos_4:Pos_5_TCG": 0.0, "Pos_0:Pos_2:Pos_5_GGT": 0.0, "Pos_2:Pos_3:Pos_5_TAC": 0.0, "Pos_0:Pos_1:Pos_5_GGG": 0.0, "Pos_1:Pos_4:Pos_5_GTA": 0.0, "Pos_0:Pos_2_AA": 0.0, "Pos_0:Pos_3:Pos_4_ACG": 0.0, "Pos_0:Pos_1:Pos_2_GGT": 0.0, "Pos_2:Pos_3:Pos_5_GCG": -0.02654347487846742, "Pos_1:Pos_2:Pos_5_GGC": 0.0, "Pos_1:Pos_3:Pos_5_AAG": 0.0, "Pos_1:Pos_3:Pos_5_ACT": 0.0, "Pos_1:Pos_2:Pos_4_TTG": 0.0, "Pos_1:Pos_4_GA": 0.0, "Pos_1:Pos_2:Pos_3_AAG": 0.017638135926111985, "Pos_1:Pos_2:Pos_4_CGC": 0.0, "Pos_1:Pos_3:Pos_5_GTA": 0.0, "Pos_2:Pos_3:Pos_4_CAC": 0.0, "Pos_2:Pos_3:Pos_5_CCC": 0.0, "Pos_0:Pos_1:Pos_4_GAT": 0.0033527422638964877, "Pos_1:Pos_4:Pos_5_CAC": 0.0, "Pos_1:Pos_2:Pos_3_GCT": 0.0, "Pos_0:Pos_2:Pos_5_CAT": 0.0, "Pos_1:Pos_2:Pos_5_TCA": -0.025303208558571783, "Pos_1:Pos_3:Pos_5_TTC": 0.0, "Pos_0:Pos_1:Pos_2_TGG": 0.0, "Pos_3:Pos_5_CA": 0.0, "Pos_0:Pos_4_AC": 0.0, "Pos_3:Pos_4:Pos_5_AGC": 0.0, "Pos_3:Pos_4:Pos_5_GTT": 0.0, "Pos_2:Pos_3:Pos_5_CGC": 0.0, "Pos_1:Pos_2:Pos_4_TAA": 0.0, "Pos_1:Pos_2:Pos_3_TTT": 0.045636000199992206, "Pos_0:Pos_2:Pos_3_TAC": 0.05507391769194007, "Pos_2:Pos_3_AA": 0.1359417445611442, "Pos_0:Pos_4_GA": 0.0, "Pos_0:Pos_2:Pos_4_CAG": 0.0, "Pos_0:Pos_1:Pos_2_GCG": -0.016591509275792247, "Pos_3:Pos_5_CG": 0.0, "Pos_1:Pos_2:Pos_3_CTT": 0.0, "Pos_1:Pos_2:Pos_5_GCA": 0.020012841032854244, "Pos_1:Pos_4:Pos_5_CCA": 0.0, "Pos_1:Pos_4:Pos_5_GAG": 0.0, "Pos_0:Pos_1:Pos_4_CTC": 0.0, "Pos_0:Pos_1:Pos_5_ATA": 0.0, "Pos_0:Pos_1:Pos_5_TCT": 0.04529872693507413, "Pos_0:Pos_2_TT": 0.0, "Pos_1:Pos_3_AA": 0.0, "Pos_0:Pos_1:Pos_3_CTA": -0.06533639728889933, "Pos_0:Pos_3:Pos_5_AAG": 0.0, "Pos_0:Pos_1:Pos_3_AGG": 0.0, "Pos_0:Pos_4:Pos_5_TAG": 0.0, "Pos_2:Pos_3:Pos_5_TTC": 0.0, "Pos_0:Pos_3:Pos_4_TCT": 0.06088540778524578, "Pos_1:Pos_2:Pos_4_GAA": 0.0, "Pos_2:Pos_3_TT": 0.0, "Pos_2:Pos_4:Pos_5_TTA": 0.0, "Pos_1:Pos_2:Pos_5_GCT": 0.0, "Pos_1:Pos_2:Pos_3_ATC": 0.0, "Pos_0:Pos_3:Pos_5_TAG": 0.07467664234175739, "Pos_0:Pos_1:Pos_4_AAG": 0.0, "Pos_1:Pos_3:Pos_5_CAG": -0.13106908711449636, "Pos_0:Pos_2:Pos_3_GTC": 0.010033531875066951, "Pos_2:Pos_3:Pos_5_TGT": 0.08365490674149832, "Pos_2:Pos_3:Pos_4_TGT": 0.0, "Pos_1:Pos_2:Pos_4_AAT": 0.11409315288626769, "Pos_1:Pos_3:Pos_4_CTC": 0.0, "Pos_3:Pos_4:Pos_5_AGA": 0.1922833502964393, "Pos_4:Pos_5_GC": 0.0, "Pos_3:Pos_4_GT": 0.0, "Pos_1:Pos_4:Pos_5_CGT": 0.0, "Pos_3:Pos_4:Pos_5_GCA": 0.0, "Pos_0:Pos_2:Pos_3_TCG": 0.0, "Pos_1:Pos_2:Pos_3_GGA": 0.0, "Pos_0:Pos_4_TC": 0.0, "Pos_3:Pos_4:Pos_5_CGT": 0.0, "Pos_0:Pos_4:Pos_5_GTA": 0.0, "Pos_2:Pos_4:Pos_5_GCA": 0.0, "Pos_2:Pos_4:Pos_5_ATA": 0.0, "Pos_1:Pos_3:Pos_5_ATC": 0.0, "Pos_1:Pos_2_CC": 0.0, "Pos_0:Pos_1:Pos_2_GTA": 0.0, "Pos_1:Pos_2_TA": 0.0074450721633988245, "Pos_2:Pos_3:Pos_4_GTA": 0.0, "Pos_0:Pos_4_GT": 0.0, "Pos_1:Pos_2:Pos_5_ACG": 0.0, "Pos_1:Pos_2_GC": 0.0, "Pos_2:Pos_3:Pos_5_GAC": 0.0, "Pos_1:Pos_2:Pos_4_GTG": 0.0, "Pos_0:Pos_3:Pos_4_ATA": 0.0, "Pos_0:Pos_1:Pos_4_CTT": 0.0, "Pos_0:Pos_1:Pos_5_ACT": 0.0, "Pos_0:Pos_4:Pos_5_CCG": 0.0, "Pos_0:Pos_1:Pos_4_GGA": 0.0, "Pos_2:Pos_4:Pos_5_CTT": 0.0, "Pos_0:Pos_2:Pos_4_GTC": 0.006333828515777154, "Pos_1:Pos_3:Pos_5_CAT": 0.057137566652331453, "Pos_2:Pos_5_CA": 0.0, "Pos_0:Pos_2:Pos_4_CTT": 0.0, "Pos_1:Pos_3:Pos_4_CCT": -0.01584200189837363, "Pos_0:Pos_1:Pos_4_CTA": 0.0, "Pos_2:Pos_4_GT": 0.0, "Pos_2:Pos_5_CG": 0.0, "Pos_1:Pos_2:Pos_5_CAC": 0.0, "Pos_4_G": 0.0, "Pos_0:Pos_3:Pos_4_AGA": 0.0, "Pos_1:Pos_2:Pos_3_CGT": 0.0, "Pos_0:Pos_3:Pos_4_GTA": 0.0, "Pos_2:Pos_3:Pos_4_GAA": 0.0, "Pos_0:Pos_1:Pos_5_GCG": 0.0, "Pos_1:Pos_4_AA": 0.0, "Pos_1:Pos_3:Pos_5_CTG": 0.0, "Pos_0:Pos_2_GA": 0.0, "Pos_1:Pos_2:Pos_3_CAA": 0.002546471022555102, "Pos_0:Pos_3_GG": 0.0, "Pos_2:Pos_4_AA": 0.0, "Pos_1:Pos_4:Pos_5_GGC": 0.0576061908964457, "Pos_0:Pos_1:Pos_2_TGC": 0.0, "Pos_2:Pos_3:Pos_5_ATA": 0.0, "Pos_1_G": -0.039943499658256616, "Pos_0:Pos_1:Pos_2_ATC": 0.0, "Pos_0:Pos_2:Pos_5_AAA": 0.0, "Pos_2:Pos_3:Pos_4_ACC": 0.0, "Pos_3:Pos_4:Pos_5_CGG": 0.0, "Pos_2:Pos_3:Pos_4_TCC": 0.18142448235217062, "Pos_0:Pos_2:Pos_5_ACG": 0.0, "Pos_1:Pos_4:Pos_5_GGG": -0.04476394362848517, "Pos_2:Pos_3:Pos_5_AAT": 0.0, "Pos_0:Pos_4:Pos_5_AAC": 0.0, "Pos_1:Pos_3:Pos_5_TGA": 0.0, "Pos_0:Pos_2:Pos_4_CCG": 0.041565280879465934, "Pos_1:Pos_4:Pos_5_ACG": 0.0, "Pos_1:Pos_2:Pos_4_ACG": 0.0, "Pos_0:Pos_2:Pos_4_CTA": 0.0, "Pos_0:Pos_1:Pos_4_CGT": 0.0, "Pos_1:Pos_2:Pos_5_CGG": 0.0, "Pos_2:Pos_4:Pos_5_AAC": -0.0970467446278794, "Pos_0:Pos_1:Pos_3_TTG": 0.0, "Pos_0:Pos_1:Pos_3_ATT": 0.07195683017838389, "Pos_0:Pos_1:Pos_4_TAT": 0.0, "Pos_0:Pos_4:Pos_5_CGA": 0.06850023176177272, "Pos_0:Pos_3:Pos_5_CTT": 0.0, "Pos_1:Pos_2:Pos_5_CCC": 0.0, "Pos_1:Pos_3:Pos_4_GTT": 0.0, "Pos_0:Pos_1:Pos_5_CTA": 0.0, "Pos_1:Pos_3:Pos_4_TCC": 0.022996261672296556, "Pos_1:Pos_2:Pos_3_CTG": 0.016221655666094494, "Pos_0:Pos_2:Pos_5_GCG": 0.0, "Pos_0:Pos_1:Pos_4_ACA": 0.0, "Pos_0:Pos_2:Pos_3_ACC": 0.0, "Pos_1:Pos_3:Pos_5_TAT": 0.0, "Pos_1:Pos_3:Pos_4_GCC": -0.05907963751845859, "Pos_4:Pos_5_AT": -0.008486358855006624, "Pos_2:Pos_4:Pos_5_GCC": 0.0, "Pos_1:Pos_2:Pos_5_ACA": 0.0, "Pos_1:Pos_5_AA": 0.0, "Pos_0:Pos_2:Pos_5_GCT": 0.0, "Pos_1_A": 0.0, "Pos_0:Pos_1:Pos_2_GTG": 0.16356260193292885, "Pos_0_C": 0.0, "Pos_2:Pos_4:Pos_5_CGA": 0.06791804385817814, "Pos_1:Pos_2:Pos_5_ACC": 0.0, "Pos_0:Pos_1:Pos_2_CGC": 0.09933788680484344, "Pos_2:Pos_3:Pos_4_AAC": 0.0, "Pos_0:Pos_2:Pos_4_TAA": 0.0, "Pos_0:Pos_1:Pos_5_ATG": 0.0, "Pos_0:Pos_1:Pos_5_CCC": 0.0, "Pos_2:Pos_3:Pos_4_TGG": 0.0, "Pos_0:Pos_3:Pos_5_TAC": 0.0, "Pos_1:Pos_2_CT": 0.0, "Pos_1:Pos_2:Pos_3_GAG": 0.0, "Pos_0:Pos_2:Pos_4_TCT": 0.0, "Pos_3:Pos_4:Pos_5_ACA": -0.1774581030972413, "Pos_0:Pos_2:Pos_5_TAC": 0.0, "Pos_1:Pos_2:Pos_3_TGG": 0.03025966954204839, "Pos_0:Pos_3:Pos_4_CAC": 0.0, "Pos_0:Pos_1:Pos_5_TGT": -0.033115745961083874, "Pos_0:Pos_1:Pos_2_GCC": 0.0, "Pos_3:Pos_4:Pos_5_GTG": -0.1688892629745795, "Pos_0:Pos_3:Pos_4_GGG": 0.0, "Pos_0:Pos_1:Pos_4_CGC": 0.0, "Pos_2:Pos_3:Pos_4_TAG": 0.0, "Pos_2:Pos_3:Pos_5_TAG": 0.0, "Pos_0:Pos_3:Pos_4_GTC": 0.0, "Pos_0:Pos_2:Pos_3_CTG": 0.0, "Pos_1:Pos_2:Pos_3_AGT": 0.0, "Pos_1:Pos_2:Pos_4_CCA": 0.0, "Pos_0:Pos_1_GT": 0.0, "Pos_1:Pos_4:Pos_5_AGC": 0.0, "Pos_2:Pos_3:Pos_4_TCT": 0.018464340099123254, "Pos_0:Pos_2_CG": 0.0, "Pos_0:Pos_2:Pos_4_CGT": 0.15962622615043323, "Pos_0:Pos_1:Pos_2_ATA": 0.0, "Pos_0:Pos_3:Pos_4_GGC": 0.0, "Pos_2:Pos_5_AC": 0.0, "Pos_2:Pos_3:Pos_5_ATG": 0.0, "Pos_1:Pos_2:Pos_4_ACA": 0.0, "Pos_0:Pos_1:Pos_5_AAA": -0.03656852371889554, "Pos_2:Pos_4:Pos_5_TCA": 0.0, "Pos_0:Pos_3:Pos_4_AGG": 0.0, "Pos_3:Pos_5_AA": 0.0, "TtoG": 0.0963389991227033, "Pos_0:Pos_4:Pos_5_GTT": 0.0, "Pos_0:Pos_4:Pos_5_GGA": 0.0, "Pos_3:Pos_4_AC": 0.0, "Pos_1:Pos_3_GG": -0.016956217401291798, "Pos_0:Pos_2:Pos_3_TTT": 0.12487075345422251, "Pos_2:Pos_3_AC": 0.0, "Pos_0:Pos_1:Pos_4_TCT": 0.0, "Pos_1:Pos_4:Pos_5_CCG": 0.0, "Pos_0:Pos_1:Pos_3_CCA": 0.0, "Pos_0:Pos_2:Pos_3_TTA": 0.0, "Pos_0:Pos_5_AT": 0.113557836354317, "Pos_1:Pos_2:Pos_5_AGT": 0.004211489987685194, "Pos_2:Pos_4:Pos_5_TTG": 0.0, "Pos_3:Pos_4:Pos_5_TGC": 0.0, "Pos_0:Pos_1:Pos_4_CCA": 0.0, "Pos_2:Pos_4:Pos_5_CAT": -0.012740562715836191, "Pos_2:Pos_3:Pos_4_CAG": 0.0, "Pos_0:Pos_1:Pos_5_GAA": 0.023923971747817945, "Pos_0:Pos_2:Pos_5_GAG": -0.07552777332271476, "Pos_2:Pos_3:Pos_4_CCT": -0.04801735870931546, "Pos_1:Pos_3:Pos_4_AGG": 0.0, "Pos_1:Pos_5_GT": -0.009452595482812416, "Pos_2:Pos_3:Pos_4_GGG": 0.0, "Pos_0:Pos_1:Pos_3_GTG": 0.12522644019247076, "Pos_0:Pos_2:Pos_5_CCC": 0.0, "Pos_0:Pos_1:Pos_5_ACC": 0.0, "Pos_0:Pos_1:Pos_2_TTG": 0.11095416177704644, "Pos_0:Pos_2:Pos_3_CAC": 0.0, "Pos_1:Pos_3:Pos_5_GTT": 0.0, "Pos_2:Pos_3:Pos_4_AGA": 0.0, "Pos_0:Pos_2_GG": 0.0, "Pos_0:Pos_3:Pos_4_CAT": 0.0, "Pos_1:Pos_2:Pos_3_ACA": 0.0, "Pos_1:Pos_2:Pos_4_CTA": 0.0, "Pos_0:Pos_2:Pos_5_CTG": -0.2292737389564938, "Pos_0:Pos_1:Pos_5_AGC": 0.0, "Pos_0:Pos_4:Pos_5_AAG": 0.0, "Pos_0:Pos_1:Pos_3_GAC": 0.0, "Pos_0:Pos_4:Pos_5_CCC": 0.0, "Pos_0:Pos_2:Pos_5_CTC": 0.0, "Pos_1:Pos_3:Pos_5_GAA": -0.13990805359310302, "Pos_1:Pos_2:Pos_4_GGC": 0.0, "Pos_1:Pos_4:Pos_5_TAC": 0.0, "Pos_1:Pos_3:Pos_4_CTG": -0.10818640682029862, "Pos_1:Pos_4:Pos_5_GGT": 0.0, "Pos_0:Pos_2:Pos_5_GAT": 0.0, "Pos_3:Pos_4_TC": 0.0, "Pos_2:Pos_3_CA": -0.007448388466806199, "Pos_1:Pos_3:Pos_5_TGC": 0.0, "Pos_1:Pos_2:Pos_3_TCC": 0.0, "Pos_1:Pos_2:Pos_4_GGT": 0.017553167716381223, "Pos_1:Pos_4:Pos_5_CGC": 0.0, "Pos_0:Pos_2:Pos_3_CGA": 0.0, "Pos_1:Pos_4:Pos_5_CAA": 0.011017105743956824, "Pos_0:Pos_1:Pos_3_GGA": -0.03770712891375066, "Pos_1:Pos_4:Pos_5_GAC": 0.07657404841052978, "Pos_0:Pos_2:Pos_3_ACG": 0.0, "Pos_1:Pos_3:Pos_4_ACT": 0.0, "Pos_3:Pos_4:Pos_5_AAC": 0.03164850727642294, "Pos_1:Pos_2:Pos_3_ATA": 0.0, "Pos_0:Pos_2:Pos_4_GAT": 0.0, "Pos_0:Pos_1:Pos_3_TTC": 0.0, "Pos_1:Pos_2:Pos_4_GAG": 0.0, "Pos_1:Pos_2:Pos_5_GAG": 0.0, "Pos_0:Pos_4_TG": 0.0, "Pos_2:Pos_3:Pos_5_GTG": 0.003494528727504015, "Pos_0:Pos_3:Pos_4_AAC": 0.0, "Pos_1:Pos_2_AA": 0.0, "Pos_1:Pos_4:Pos_5_GTT": 0.0, "Pos_1:Pos_3:Pos_5_AGA": 0.0, "Pos_1:Pos_3:Pos_5_GGA": 0.0, "Pos_0:Pos_1:Pos_2_GAG": 0.0, "Pos_2:Pos_4:Pos_5_GAG": 0.0, "Pos_1:Pos_2:Pos_4_CAT": 0.0, "Pos_0:Pos_2:Pos_3_ATG": 0.0, "Pos_0:Pos_3:Pos_4_TAA": 0.0, "Pos_0:Pos_2:Pos_5_CTT": 0.1788631611972212, "Pos_2:Pos_4:Pos_5_TAG": 0.0, "Pos_0:Pos_3:Pos_5_TTG": 0.0, "Pos_3:Pos_4_CC": 0.0, "Pos_3:Pos_5_GG": -0.011046874546732173, "Pos_0:Pos_1:Pos_2_CAT": 0.0, "TtoC": 0.10294019097052501, "Pos_2:Pos_3:Pos_4_TAA": 0.0, "Pos_3:Pos_4:Pos_5_GTA": 0.1231109186929221, "Pos_2:Pos_3:Pos_5_CCG": 0.0, "Pos_0:Pos_3:Pos_5_CCG": 0.0, "Pos_0:Pos_1:Pos_4_AAC": 0.0, "Pos_1:Pos_4:Pos_5_AAA": 0.0, "Pos_0:Pos_1:Pos_2_AGT": 0.0, "Pos_2:Pos_5_AG": 0.0, "Pos_0:Pos_2:Pos_3_TCA": 0.0, "Pos_0:Pos_2:Pos_5_AAT": 0.0, "Pos_0:Pos_3:Pos_4_CCC": 0.0, "Pos_0:Pos_2:Pos_4_AAA": -0.0722647725176463, "Pos_1:Pos_4:Pos_5_GAT": 0.0, "Pos_0:Pos_4:Pos_5_TGT": 0.0498577423781477, "Pos_4:Pos_5_AG": -0.03634045918356673, "Pos_2:Pos_3:Pos_4_GAT": 0.0, "Pos_0:Pos_1:Pos_5_GTG": 0.0, "Pos_1:Pos_2:Pos_4_GCT": 0.0, "Pos_1:Pos_3:Pos_4_CCG": 0.003160043300644157, "Pos_1:Pos_3:Pos_5_GCA": 0.0, "Pos_2:Pos_3:Pos_4_TGC": 0.0, "Pos_1:Pos_2:Pos_3_GTT": 0.0, "Pos_0:Pos_3:Pos_5_AGG": 0.0, "Pos_0:Pos_2:Pos_5_TCT": 0.0, "Pos_0:Pos_2:Pos_5_CCT": -0.019704808917405996, "Pos_0:Pos_3:Pos_4_TCG": 0.0, "Pos_1:Pos_2_GT": -0.01436998104338847, "Pos_2:Pos_3:Pos_4_GCC": 0.0, "Pos_2:Pos_4:Pos_5_TAC": 0.04737161502306122, "Pos_2:Pos_3:Pos_5_TCC": 0.016173624535125435, "Pos_0:Pos_3:Pos_5_CAC": 0.0, "Pos_2:Pos_4:Pos_5_CCG": 0.0, "Pos_0:Pos_5_GA": 0.007911207338369607, "Pos_0:Pos_1:Pos_5_TCC": 0.0, "Pos_2:Pos_3:Pos_5_TTA": 0.17916651071755185, "Pos_1:Pos_3:Pos_4_ATG": 0.02474402723769555, "Pos_0:Pos_1:Pos_3_CTG": 0.0, "Pos_0:Pos_3:Pos_4_GTG": 0.0}