{"Pos_0:Pos_1:Pos_3_AGA": 0.040413254814605795, "AtoT": 0.41760801995175556, "Pos_0:Pos_1:Pos_3_GCA": -0.04437328861061109, "Pos_1:Pos_2:Pos_3_TCA": 0.0, "Pos_0:Pos_1:Pos_2_ATT": 0.0, "Pos_1:Pos_2:Pos_3_GCA": 0.002468930571770287, "Pos_0:Pos_1_TA": 0.0, "Pos_0:Pos_1_CT": 0.0, "Pos_1:Pos_2_AT": 0.0, "Pos_0:Pos_1:Pos_2_CGA": -0.009797552511424504, "Pos_0:Pos_1:Pos_3_CCA": 0.0, "Pos_1:Pos_3_CG": 0.0, "Pos_0:Pos_1:Pos_3_CAG": 0.0, "Pos_0:Pos_1:Pos_2_GCA": 0.0, "Pos_0:Pos_1:Pos_3_AAG": 0.0, "Pos_1:Pos_3_CT": 0.0, "Pos_0:Pos_1_TG": 0.032345738273922696, "Pos_0:Pos_1:Pos_3_GGA": 0.0, "Pos_1:Pos_2:Pos_3_CTA": -0.026129225734852317, "Pos_0:Pos_2:Pos_3_ATT": 0.06380081655733487, "GtoA": -0.4000854780743964, "Pos_0:Pos_1_GA": -0.05912776628166368, "Pos_1:Pos_2_GC": 0.06108022230012632, "Pos_0:Pos_1:Pos_2_CAG": 0.0, "CtoA": -0.01277553341420438, "Pos_0:Pos_3_GA": -0.012448573005964235, "Pos_0:Pos_2:Pos_3_GTA": -0.007726540952105187, "Pos_1:Pos_2_AG": -0.03593527807186355, "Pos_0:Pos_3_CG": 0.0, "Pos_0:Pos_1:Pos_3_GTG": -0.02098395464756478, "Pos_1:Pos_2:Pos_3_AGG": 0.0, "Pos_0:Pos_2:Pos_3_CTG": -0.09290818513509745, "Pos_0:Pos_1:Pos_3_CGG": -0.04475848415469762, "Pos_1:Pos_2:Pos_3_GAC": 0.0, "Pos_1:Pos_2_TC": 0.0, "Pos_2:Pos_3_CC": 0.0, "Pos_0:Pos_1:Pos_2_CTC": 0.0, "Pos_0:Pos_1:Pos_3_AAC": -0.019108099773106346, "Pos_1:Pos_2:Pos_3_GTC": 0.014952380440481595, "Pos_0:Pos_3_TC": 0.0, "Pos_0:Pos_1:Pos_2_TCC": 0.0, "Pos_0:Pos_2:Pos_3_AAA": 0.0, "Pos_0:Pos_1:Pos_3_ACT": 0.0, "Pos_0:Pos_1:Pos_3_ACA": -0.07129973024936759, "Pos_0:Pos_2_TG": 0.0, "Pos_0:Pos_1:Pos_3_AAA": 0.01728400207086204, "Pos_0:Pos_1:Pos_2_CTT": -0.020203631306515302, "Pos_1:Pos_2:Pos_3_CGT": 0.0, "Pos_0:Pos_1:Pos_2_ATG": -0.05101285480073396, "Pos_0:Pos_1:Pos_2_AGA": 0.0, "Pos_0:Pos_1:Pos_3_CCG": 0.027063878161562832, "Pos_0:Pos_1:Pos_2_TGT": 0.0, "Pos_0:Pos_1_AA": 0.0, "Pos_1:Pos_2:Pos_3_GAT": 0.0, "Pos_0:Pos_3_GG": 0.0, "Pos_1:Pos_3_TC": -0.008106237505963905, "CtoG": -0.507735037678487, "Pos_0:Pos_1:Pos_2_ATC": 0.034858198443213036, "Pos_0:Pos_3_AG": 0.0, "Pos_0:Pos_1:Pos_2_GTC": -0.009636874086958184, "Pos_2_G": -0.14420525318193494, "Pos_1:Pos_2:Pos_3_TGA": -0.0018436477668462422, "Pos_0:Pos_1:Pos_2_ACG": 0.0, "Pos_1:Pos_2:Pos_3_CCC": 0.01684740187227539, "Pos_1_G": 0.0035976029553654878, "Pos_0:Pos_1:Pos_3_CCT": -0.0136746841231799, "Pos_0:Pos_1:Pos_3_GGG": 0.0, "Pos_1:Pos_2_CG": 0.0, "Pos_0:Pos_2:Pos_3_GGG": 0.0, "Pos_0:Pos_1:Pos_3_CCC": -0.06361544181851239, "Pos_0:Pos_2:Pos_3_ACA": 0.0013560994607533935, "Pos_0:Pos_1:Pos_2_GCC": 0.0, "Pos_0:Pos_1:Pos_2_GGG": 0.0, "Pos_0:Pos_1:Pos_2_CGC": 0.012748609308567917, "Pos_0:Pos_1:Pos_3_TGA": 0.0, "Pos_0:Pos_1:Pos_2_AAA": 0.0029846082049076574, "Pos_0:Pos_1:Pos_2_TCT": 0.0, "Pos_2:Pos_3_GA": -0.10320364314290366, "Pos_1:Pos_2:Pos_3_GTT": 0.0, "Pos_1:Pos_3_TT": 0.0, "Pos_1:Pos_2:Pos_3_TAG": 0.0, "Pos_1:Pos_3_GT": 0.0, "Pos_1:Pos_2_TT": 0.0, "Pos_0:Pos_1:Pos_3_GTA": 0.0, "Pos_0:Pos_2:Pos_3_GTT": -0.046894153951147224, "Pos_0:Pos_1:Pos_2_AGT": 0.09319766994711111, "Pos_0:Pos_1_GG": 0.0, "Pos_0:Pos_1_GC": 0.0, "Pos_1:Pos_2:Pos_3_ACA": 0.021944501774298502, "Pos_1:Pos_2:Pos_3_TCG": -0.06383040332141848, "Pos_0:Pos_2:Pos_3_GCA": 0.0, "Pos_0:Pos_2:Pos_3_AAC": 0.0, "Pos_2:Pos_3_CT": 0.0, "Pos_0:Pos_2_GA": 0.0, "Pos_1:Pos_2:Pos_3_TTA": 0.0014808160864189744, "Pos_1:Pos_2:Pos_3_GCG": 0.0020728737509321314, "Pos_0:Pos_2:Pos_3_GTG": 0.0, "Pos_1:Pos_2:Pos_3_TCT": 0.0, "Pos_1:Pos_3_AC": 0.0, "Pos_0:Pos_1:Pos_2_TAG": -0.05649123022650398, "Pos_1:Pos_2:Pos_3_TGT": 0.0, "Pos_0:Pos_2:Pos_3_TCG": 0.0, "Pos_2:Pos_3_TA": 0.0, "Pos_0:Pos_1:Pos_2_CGT": -0.008840397246236557, "Pos_0:Pos_1_AG": 0.0, "Pos_1:Pos_2:Pos_3_ACC": -0.04656462792759531, "Pos_0:Pos_1:Pos_2_GCT": -0.04966227977010066, "Pos_0:Pos_2:Pos_3_AGT": -0.04775181763362677, "Pos_0:Pos_2:Pos_3_ATG": 0.042664759856032235, "Pos_1:Pos_2:Pos_3_TCC": 0.0, "Pos_0:Pos_1:Pos_2_CTG": 0.028355984596573184, "Pos_0:Pos_1_TT": 0.0, "Pos_0:Pos_3_CC": 0.0, "GtoC": -0.4220541738434621, "TtoG": 0.04729877808357345, "Pos_0:Pos_1:Pos_3_AAT": 0.03713494677213994, "Pos_0:Pos_2:Pos_3_GAA": 0.0, "Pos_0:Pos_1:Pos_2_TAC": 0.0, "Pos_0:Pos_1:Pos_2_TAA": 0.012085664429654119, "Pos_0:Pos_1:Pos_2_ACC": -0.061437733347121014, "Pos_0:Pos_1:Pos_3_CAC": 0.004983304859859294, "Pos_0:Pos_2:Pos_3_CCA": 0.0, "Pos_0:Pos_1:Pos_2_GAG": 0.0, "Pos_0:Pos_1:Pos_2_AGC": 0.04827855474699194, "Pos_0:Pos_1:Pos_3_ATA": -0.0032059900301593166, "Pos_0:Pos_2:Pos_3_GGA": 0.0, "Pos_0:Pos_1:Pos_2_GCG": 0.0, "Pos_0:Pos_2:Pos_3_AGC": 0.000951339074568925, "Pos_0:Pos_1:Pos_2_CCT": 0.014893592548099223, "Pos_0:Pos_2:Pos_3_AGA": -0.002386836514203426, "Pos_0:Pos_2:Pos_3_TGC": 0.0, "Pos_1:Pos_2:Pos_3_CAT": 0.0, "Pos_1:Pos_2_AC": 0.0, "Pos_0:Pos_2:Pos_3_TGT": -0.024419429932150977, "Pos_0:Pos_1:Pos_3_AGT": 0.0, "Pos_1:Pos_3_CC": 0.0, "Pos_1:Pos_2:Pos_3_ATT": 0.010844842935799936, "Pos_1:Pos_3_AT": 0.0, "Pos_2:Pos_3_GT": 0.0, "Pos_1:Pos_3_GG": 0.0, "Pos_1:Pos_2:Pos_3_AGC": 0.0, "Pos_1:Pos_2:Pos_3_TTG": 0.0, "Pos_0:Pos_1:Pos_3_TAC": 0.0, "Pos_0:Pos_2_GC": 0.0, "Pos_2:Pos_3_TC": 0.0, "Pos_1:Pos_2:Pos_3_AAA": 0.0, "Pos_0:Pos_1:Pos_3_TGG": 0.0, "Pos_1_C": -0.12992111729937794, "Pos_0:Pos_2:Pos_3_ATC": -0.004160279792213256, "Pos_1:Pos_2:Pos_3_AAC": 0.0053053445879720105, "Pos_1_T": 0.0, "Pos_1:Pos_3_GA": 0.0, "Pos_1:Pos_2:Pos_3_TAT": 0.0, "Pos_0:Pos_1:Pos_3_AGG": 0.09085447668174557, "Pos_0:Pos_1:Pos_3_TCC": -0.021876618096920993, "Pos_0:Pos_1:Pos_2_GTA": -0.022794894590905213, "Pos_0:Pos_1:Pos_2_CTA": 0.0, "Pos_1:Pos_2:Pos_3_CGA": 0.0, "Pos_0:Pos_2:Pos_3_TAG": 0.0, "Pos_2_T": 0.0, "Pos_0:Pos_1:Pos_2_ACT": 0.0, "Pos_0:Pos_1:Pos_3_TTT": 0.03834185946642762, "Pos_1_A": 0.0, "Pos_0:Pos_1:Pos_3_TTC": 0.0, "Pos_0:Pos_3_GT": 0.0, "Pos_0:Pos_2:Pos_3_TAC": 0.0, "Pos_0:Pos_1:Pos_2_TGC": 0.06255638999603522, "Pos_0:Pos_2:Pos_3_TAT": 0.013222108496028655, "Pos_0:Pos_1:Pos_3_CAA": 0.036563132897399875, "Pos_1:Pos_2:Pos_3_GAG": 0.002426796715181504, "Pos_2_A": 0.0, "Pos_0:Pos_2_CT": 0.0, "Pos_0:Pos_2:Pos_3_CCC": 0.0, "Pos_0:Pos_1:Pos_2_TGG": 0.021867526036460683, "Pos_1:Pos_3_AA": 0.0, "Pos_0:Pos_1:Pos_3_GAT": 0.0, "Pos_0:Pos_3_CT": 0.0, "Pos_1:Pos_2:Pos_3_GGA": 0.0, "Pos_1:Pos_2_GG": 0.0, "Pos_1:Pos_2:Pos_3_GGC": 0.11517296960862299, "Pos_1:Pos_2:Pos_3_TGG": 0.07739172058149082, "Pos_0:Pos_1:Pos_2_CAT": 0.0, "Pos_0:Pos_2_AA": 0.0, "Pos_0:Pos_2:Pos_3_GGC": -0.020256643406367243, "Pos_0:Pos_2_CC": 0.0, "Pos_1:Pos_2:Pos_3_CCT": -0.006877648684538374, "Pos_1:Pos_2:Pos_3_GAA": 0.010959068847463145, "Pos_0:Pos_1_TC": 0.0, "Pos_1:Pos_2_AA": 0.0, "Pos_1:Pos_2:Pos_3_CTG": 0.0, "Pos_0:Pos_1_CG": 0.0, "Pos_0:Pos_1:Pos_3_GGC": 0.0, "Pos_0:Pos_1:Pos_2_CCA": 0.0, "Pos_1:Pos_2:Pos_3_TGC": 0.0, "Pos_1:Pos_2_CT": 0.0, "Pos_0:Pos_2:Pos_3_CAA": 0.0192574242862416, "Pos_0:Pos_1:Pos_3_TGT": 0.0, "Pos_0:Pos_1:Pos_2_GAC": 0.0, "Pos_0:Pos_3_TA": 0.0, "Pos_0:Pos_3_AC": 0.0, "Pos_0:Pos_2_CG": 0.0, "Pos_0_G": -0.03490618560554744, "Pos_0:Pos_1:Pos_3_TTG": 0.016363411126396558, "Pos_0:Pos_2:Pos_3_GTC": 0.011297752013749367, "Pos_0:Pos_2_GT": 0.0, "Pos_1:Pos_2:Pos_3_ACG": 0.0, "Pos_0:Pos_2:Pos_3_ACT": 0.002608932735542001, "Pos_1:Pos_2:Pos_3_GGG": 0.0, "Pos_1:Pos_2:Pos_3_TTC": 0.0, "Pos_0:Pos_1:Pos_3_GCG": -0.013582095531318738, "Pos_0:Pos_2:Pos_3_AAT": 0.0, "Pos_1:Pos_2:Pos_3_ATG": 0.008044606133035535, "Pos_0:Pos_1:Pos_3_ACC": 0.11346838158576868, "Pos_0:Pos_1_CC": 0.0, "Pos_0:Pos_2_AC": 0.0, "Pos_0:Pos_2_GG": -0.02089026311169475, "Pos_0:Pos_2:Pos_3_TAA": 0.0, "Pos_0:Pos_1:Pos_3_TGC": 0.019304235019940046, "Pos_0:Pos_2:Pos_3_GGT": 0.0, "Pos_0:Pos_2:Pos_3_ACG": -0.029678800623358783, "Pos_0:Pos_1_AC": 0.0, "CtoT": -0.3817447706320899, "Pos_0:Pos_1:Pos_3_TAT": -0.004045545802189354, "Pos_1:Pos_2:Pos_3_GTA": 0.0, "Pos_0:Pos_2:Pos_3_GCT": 0.0, "GC_feature": -0.0820953297850703, "Pos_0:Pos_3_AT": 0.0, "Pos_0:Pos_1:Pos_3_ACG": -0.03980816717490398, "Pos_0:Pos_2:Pos_3_CAC": -0.012418947486686404, "Pos_0_A": 0.0, "Pos_1:Pos_2_GA": 0.0, "Pos_0:Pos_1:Pos_3_GAA": 0.0, "Pos_0:Pos_2:Pos_3_CTA": 0.0, "Pos_0:Pos_2:Pos_3_CTC": 0.01900232857595471, "Pos_0:Pos_1:Pos_3_GTT": 0.0, "Pos_0:Pos_1:Pos_2_TCA": 0.0, "Pos_0:Pos_1:Pos_2_AAG": 0.0, "Pos_3_C": 0.0, "Pos_0:Pos_2_AT": 0.0, "Pos_0:Pos_1:Pos_2_GAA": 0.0, "Pos_0:Pos_1:Pos_2_TTA": 0.0, "Pos_0:Pos_2:Pos_3_ACC": 0.0, "Pos_0:Pos_1:Pos_2_AAT": 0.0003992878826727336, "Pos_0:Pos_1:Pos_2_CCG": 0.0, "Pos_1:Pos_2:Pos_3_ATA": -0.05147427094044363, "Pos_2:Pos_3_TG": 0.0, "Pos_0:Pos_1:Pos_2_TTC": 0.0, "Pos_0:Pos_1:Pos_3_CGT": 0.0, "Pos_0:Pos_2:Pos_3_GAG": 0.0, "Pos_0:Pos_2:Pos_3_GCG": -0.039750542416190866, "Pos_2:Pos_3_AT": -0.03445726045725842, "Pos_0:Pos_1:Pos_2_GAT": -0.007918436459397993, "Pos_0:Pos_3_TG": 0.0, "Pos_0:Pos_1:Pos_3_AGC": 0.0, "Pos_1:Pos_2:Pos_3_CTT": 0.044519777811093356, "TtoA": 0.4671328991010067, "Pos_2:Pos_3_AA": 0.0, "Pos_1:Pos_2:Pos_3_AGA": 0.0, "Pos_3_A": 0.0, "Pos_1:Pos_2_CA": -0.04107704049067, "Pos_0:Pos_1:Pos_2_TAT": 0.0, "Pos_0:Pos_2:Pos_3_CGC": 0.0, "Pos_0:Pos_1:Pos_3_CGC": 0.0, "Pos_0:Pos_1:Pos_3_CTC": -0.055440474891091114, "Pos_0:Pos_1:Pos_3_TAA": 0.012468087824462319, "Pos_2:Pos_3_GG": 0.0, "Pos_0_T": 0.04305596869937135, "Pos_0:Pos_1:Pos_2_GTT": 0.017275175257267794, "Pos_1:Pos_3_AG": 0.0, "Pos_0:Pos_2:Pos_3_CTT": 0.0, "Pos_1:Pos_2:Pos_3_GTG": -0.044517614000563616, "Pos_1:Pos_2:Pos_3_CCA": 0.0, "Pos_0:Pos_2:Pos_3_TTC": 0.0, "AtoG": 0.015017213990361123, "Pos_3_G": 0.0, "Pos_1:Pos_2:Pos_3_CCG": -0.026679892336491325, "Pos_0:Pos_1:Pos_2_GGA": 0.03056467621024272, "Pos_0:Pos_1:Pos_3_CTG": 0.0, "Pos_0:Pos_2_AG": 0.0, "Pos_1:Pos_3_TG": 0.0, "Pos_0:Pos_1:Pos_3_ATC": -0.028743439323861947, "Pos_1:Pos_3_TA": 0.0, "Pos_1:Pos_2:Pos_3_AAT": 0.0, "Pos_0:Pos_2:Pos_3_GAT": 0.0, "Pos_1:Pos_2:Pos_3_TAC": -0.10878067132510694, "Pos_0:Pos_1:Pos_3_TTA": -0.049082190839124164, "Pos_0:Pos_1:Pos_2_CAA": 0.005759240499028745, "Pos_1:Pos_3_CA": 0.0, "Pos_0:Pos_1:Pos_3_TCA": 0.016004397911788346, "Pos_0:Pos_2:Pos_3_TTG": 0.0, "Pos_0:Pos_2:Pos_3_CGA": 0.0, "Pos_0:Pos_1:Pos_2_CAC": 0.0, "Pos_0:Pos_1:Pos_2_TTT": 0.00932344719771188, "Pos_0:Pos_2:Pos_3_GAC": 0.05362610829932192, "Pos_0:Pos_3_GC": 0.0, "Pos_0:Pos_1:Pos_2_AAC": 0.0, "Pos_0_C": 0.0, "Pos_0:Pos_1:Pos_2_TTG": 0.0, "Pos_0:Pos_2:Pos_3_TCC": 0.0030398094850332047, "Pos_0:Pos_2:Pos_3_CGT": 0.0, "Pos_1:Pos_2:Pos_3_GCC": 0.0, "Pos_0:Pos_1_GT": 0.0, "Pos_1:Pos_2_TG": 0.0, "Pos_0:Pos_2:Pos_3_TCT": 0.0, "Pos_0:Pos_1:Pos_3_GCT": 0.0, "Pos_0:Pos_2_TT": 0.0, "Pos_0:Pos_1:Pos_3_ATT": 0.0, "Pos_2:Pos_3_CA": 0.039983113716651815, "Pos_1:Pos_2:Pos_3_ATC": 0.0, "Pos_1:Pos_3_GC": 0.0, "Pos_0:Pos_1:Pos_3_GAC": -0.02336859115377983, "Pos_1:Pos_2_GT": 0.0, "Pos_0:Pos_2:Pos_3_TGG": 0.0, "Pos_0:Pos_3_CA": 0.0, "Pos_0:Pos_1:Pos_2_AGG": 0.0, "Pos_1:Pos_2_TA": -0.03250155224211006, "Pos_0:Pos_1:Pos_2_GTG": -0.01226369350828332, "Pos_0:Pos_1:Pos_3_TCT": 0.03581608667605522, "Pos_0:Pos_1:Pos_3_CTA": 0.0, "Pos_1:Pos_2:Pos_3_TAA": -0.035249805616586194, "Pos_0:Pos_2:Pos_3_TTT": 0.029849306963909243, "Pos_0:Pos_1:Pos_2_TCG": -0.07681875812711224, "Pos_1:Pos_2:Pos_3_CAG": 0.0, "Pos_2:Pos_3_TT": 0.0, "Pos_1:Pos_2:Pos_3_TTT": 0.0, "Pos_0:Pos_1:Pos_3_ATG": 0.0, "Pos_0:Pos_2_TA": 0.0, "Pos_0:Pos_2:Pos_3_TTA": 0.04301932976503891, "Pos_0:Pos_2:Pos_3_AAG": 0.0, "Pos_0:Pos_2:Pos_3_CAG": 0.0, "Pos_0:Pos_1:Pos_3_GAG": 0.0, "Pos_0:Pos_1:Pos_2_CCC": -0.006924965794436667, "Pos_0:Pos_1:Pos_3_CAT": 0.0, "Pos_2_C": 0.0, "Pos_0:Pos_1:Pos_2_GGT": 0.0, "Pos_0:Pos_1_CA": 0.0, "Pos_1:Pos_2:Pos_3_CGG": 0.0, "Pos_0:Pos_1:Pos_3_GCC": 0.020156572024897113, "TtoC": 0.0, "GtoT": 0.07781861925972579, "Pos_1:Pos_2:Pos_3_CAC": -0.007220329737359658, "Pos_0:Pos_2:Pos_3_CAT": -0.06174518410005996, "Pos_0:Pos_1:Pos_3_TCG": -0.003885632773542939, "Pos_0:Pos_2_CA": 0.0, "Pos_0:Pos_3_TT": 0.0, "AtoC": -0.07877539087416795, "Pos_0:Pos_1:Pos_2_GGC": 0.0, "Pos_0:Pos_1:Pos_2_CGG": -0.027164059070178617, "Pos_0:Pos_1:Pos_2_ACA": -0.028925334276109334, "Pos_0:Pos_2:Pos_3_TGA": 0.0, "Pos_0:Pos_2:Pos_3_CGG": 0.0, "Pos_0:Pos_1:Pos_3_CGA": -0.02373886572503059, "Pos_1:Pos_2:Pos_3_CAA": 0.0, "Pos_1:Pos_2:Pos_3_AAG": 0.03753086023362171, "Pos_2:Pos_3_GC": 0.0, "Pos_0:Pos_2:Pos_3_TCA": 0.0, "Pos_1:Pos_2:Pos_3_CGC": -0.027607182014388252, "Pos_0:Pos_1:Pos_3_GTC": 0.0, "Pos_0:Pos_2_TC": 0.0, "Pos_0:Pos_1:Pos_3_GGT": 0.0, "Pos_1:Pos_2:Pos_3_CTC": 0.0, "Pos_1:Pos_2:Pos_3_GCT": 0.022662935919521458, "Pos_0:Pos_3_AA": 0.0, "Pos_0:Pos_1:Pos_2_TGA": 0.04183172026100402, "Pos_1:Pos_2:Pos_3_AGT": -0.00754584834085021, "Pos_0:Pos_2:Pos_3_ATA": 0.0, "Pos_1:Pos_2:Pos_3_ACT": 0.010966414823548723, "Pos_0:Pos_2:Pos_3_AGG": 0.0059827541110337576, "Pos_3_T": 0.0, "Pos_2:Pos_3_CG": 0.0, "Pos_0:Pos_1:Pos_2_ATA": -0.004214267810678392, "Pos_0:Pos_2:Pos_3_CCT": 0.0, "Pos_2:Pos_3_AG": 0.0, "Pos_0:Pos_1_AT": 0.0, "Pos_0:Pos_1:Pos_3_CTT": 0.0, "Pos_0:Pos_2:Pos_3_GCC": 0.0, "Pos_0:Pos_1:Pos_3_TAG": 0.0, "Pos_2:Pos_3_AC": 0.0, "Pos_1:Pos_2_CC": 0.0, "Pos_0:Pos_2:Pos_3_CCG": 0.0038156390219682055, "Pos_1:Pos_2:Pos_3_GGT": 0.08558687840706096}