{"Pos_0:Pos_2_GG": 0.0, "Pos_1:Pos_3_CA": 0.0, "Pos_0:Pos_1_CT": 0.0, "Pos_3_T": 0.0, "Pos_0:Pos_2:Pos_3_CAG": 0.24520700782463173, "Pos_0:Pos_3_CT": 0.0, "Pos_0:Pos_1:Pos_3_GAG": 0.233364264567417, "Pos_1:Pos_3_AC": 0.0, "Pos_0:Pos_1:Pos_3_TTA": 0.0, "Pos_0:Pos_2:Pos_3_ACT": 0.0871024695791436, "Pos_0:Pos_2_CT": 0.0, "Pos_1:Pos_2:Pos_3_TTA": 0.0, "Pos_0:Pos_2:Pos_3_CTG": -0.36272296882995086, "Pos_0:Pos_1:Pos_2_CCA": 0.0, "Pos_0:Pos_2:Pos_3_ATG": 0.41391829985163864, "Pos_1:Pos_2:Pos_3_CAT": 0.14286718010514185, "Pos_0:Pos_2:Pos_3_TCC": 0.24211012773203155, "Pos_0:Pos_2:Pos_3_TTT": 0.006930534697138569, "Pos_0:Pos_1:Pos_2_GAA": -0.23167561632115857, "AtoC": -0.036196162788458254, "Pos_0:Pos_1:Pos_3_GCG": 0.025937105162304918, "Pos_1:Pos_2:Pos_3_CGC": 0.3266741053326744, "Pos_0:Pos_1:Pos_3_GAT": 0.0, "Pos_1:Pos_2:Pos_3_AAC": 0.0, "Pos_0:Pos_2:Pos_3_CAA": -0.14468457290439105, "Pos_0:Pos_2:Pos_3_TAA": 0.5503281771889935, "Pos_0:Pos_1_TG": 0.0, "Pos_0:Pos_1:Pos_3_GGT": 0.0, "Pos_0:Pos_2:Pos_3_AAT": -0.6272964663045177, "Pos_0:Pos_1:Pos_2_AGT": 0.2025701362800983, "Pos_1:Pos_2:Pos_3_AGT": 0.0, "Pos_1:Pos_2_CC": 0.0, "Pos_2:Pos_3_AA": -0.15890198418904286, "Pos_0:Pos_2:Pos_3_TAC": 0.0, "Pos_1:Pos_2_GA": -0.19743338979367248, "Pos_2:Pos_3_AG": 0.08524678892709053, "Pos_0:Pos_1:Pos_2_TTG": 0.17623312686368275, "Pos_1:Pos_2_GG": 0.0, "Pos_2:Pos_3_TT": 0.01296573824974465, "Pos_0:Pos_2:Pos_3_GGG": 0.24234544176296524, "Pos_2:Pos_3_CT": 0.0, "TtoC": 0.1738762427254106, "Pos_0:Pos_2_CC": 0.07415813346509247, "Pos_0:Pos_1:Pos_2_GAT": -0.02221289328560372, "Pos_0:Pos_2:Pos_3_TTG": -0.1363358340278103, "Pos_1:Pos_2:Pos_3_TGA": 0.03408068266195525, "Pos_0:Pos_2:Pos_3_CAT": 0.0, "Pos_0:Pos_1_CA": 0.0, "Pos_0:Pos_1_GA": -0.14431352580725018, "Pos_2:Pos_3_CC": 0.0, "Pos_0:Pos_2:Pos_3_TTA": 0.10209919824047324, "Pos_1:Pos_2_AG": -0.05494433748391891, "Pos_1:Pos_2:Pos_3_CGT": 0.0, "Pos_0_T": 0.0, "Pos_0:Pos_1:Pos_3_CGG": -0.0519623041169204, "Pos_0:Pos_1_CC": 0.0, "TtoA": 1.17916370356056, "Pos_1:Pos_2:Pos_3_CTG": -0.11693586736050259, "Pos_1:Pos_2:Pos_3_AAG": 0.0, "Pos_2:Pos_3_AC": 0.0, "Pos_0:Pos_1:Pos_3_AAA": -0.06817870470227799, "Pos_2:Pos_3_TG": 0.0, "Pos_0:Pos_2:Pos_3_CTA": 0.0, "Pos_0:Pos_1:Pos_2_CAT": -0.05280405036098299, "Pos_1:Pos_2:Pos_3_GGA": -0.020765183605496937, "Pos_0:Pos_1:Pos_3_CAG": -0.03961787977296756, "Pos_0:Pos_1:Pos_3_TAG": 0.004391091727720491, "Pos_0:Pos_1:Pos_3_AAT": 0.20835514682116907, "Pos_0:Pos_1:Pos_3_AGC": -0.022819117525392313, "Pos_0:Pos_1:Pos_3_CCT": 0.0, "Pos_0:Pos_3_AT": 0.0, "Pos_1:Pos_2:Pos_3_CAC": -0.2453344858548476, "Pos_3_C": 0.0, "Pos_0:Pos_2:Pos_3_ATA": -0.23259396767887203, "Pos_2:Pos_3_TC": 0.0, "Pos_1:Pos_2:Pos_3_TGT": 0.0, "Pos_0:Pos_1:Pos_2_ACT": -0.059430264023056636, "Pos_0:Pos_1:Pos_3_TGC": 0.0, "Pos_0:Pos_1:Pos_3_TGG": 0.0, "Pos_1:Pos_3_GC": 0.20411773421511256, "Pos_0:Pos_1:Pos_2_CTG": 0.073251977214674, "Pos_1:Pos_2:Pos_3_AGG": 0.0, "Pos_0:Pos_1:Pos_2_CTT": 0.0, "Pos_0:Pos_1:Pos_3_GAA": 0.0, "Pos_1:Pos_2:Pos_3_TAC": 0.0, "Pos_0:Pos_2:Pos_3_GTC": 0.0, "Pos_0:Pos_1_TC": 0.09582860033822369, "Pos_0:Pos_1:Pos_3_TTG": -0.18846633384974584, "Pos_0:Pos_2:Pos_3_AAA": 0.0, "Pos_0:Pos_2:Pos_3_CTC": 0.0, "Pos_0:Pos_2_GT": 0.0, "CtoG": -2.090332735776261, "Pos_0:Pos_3_GG": 0.0, "Pos_0:Pos_1:Pos_3_TAC": 0.0, "Pos_1:Pos_2:Pos_3_ATT": -0.13633724932993446, "Pos_1:Pos_2:Pos_3_ACG": 0.0, "Pos_0:Pos_2_TT": 0.0, "Pos_0:Pos_1:Pos_2_TCT": 0.0, "Pos_0:Pos_2:Pos_3_GTG": 0.0, "Pos_0:Pos_2_AG": -0.009495274516325517, "Pos_0:Pos_2:Pos_3_TAG": -0.17343945054979157, "Pos_0:Pos_1:Pos_2_CGT": 0.0, "Pos_1:Pos_2:Pos_3_GGC": 0.0, "Pos_0:Pos_1:Pos_2_TAG": -0.2834563372515622, "Pos_0:Pos_1:Pos_3_GGG": 0.0, "Pos_1:Pos_2:Pos_3_TAT": -0.07660538020895753, "Pos_0:Pos_1:Pos_2_ACA": -0.3386801663674048, "Pos_0:Pos_2:Pos_3_TTC": 0.0, "Pos_0:Pos_2_AT": 0.0, "Pos_1:Pos_2:Pos_3_GGG": 0.0, "Pos_0:Pos_1:Pos_2_TAC": 0.0, "Pos_1:Pos_2:Pos_3_CCT": -0.21615070441030462, "Pos_0:Pos_1_TA": 0.0, "Pos_0:Pos_1:Pos_3_GTG": -0.13827506094425576, "Pos_0_C": 0.0, "Pos_0:Pos_1:Pos_3_GGC": 0.0, "Pos_0:Pos_2:Pos_3_ATC": 0.0, "Pos_1:Pos_3_CC": 0.0, "Pos_0:Pos_2:Pos_3_AAG": 0.0, "Pos_0:Pos_1:Pos_3_GGA": 0.0, "Pos_0:Pos_1:Pos_2_TAA": 0.0, "Pos_2:Pos_3_GG": 0.0, "Pos_0:Pos_1:Pos_3_CCC": 0.0, "Pos_0:Pos_2:Pos_3_TCG": 0.0, "Pos_0:Pos_2:Pos_3_CCC": -0.29897475177550487, "Pos_0:Pos_2:Pos_3_AGG": 0.0, "Pos_0_A": 0.0, "Pos_1:Pos_2:Pos_3_GTT": 0.08678445215944244, "Pos_0:Pos_3_CG": 0.0, "GtoA": -0.46263556580830273, "Pos_1:Pos_3_GG": 0.0, "Pos_1:Pos_2:Pos_3_GTA": 0.0, "Pos_1:Pos_2_TA": 0.0, "Pos_0:Pos_2:Pos_3_TCT": -0.01181089961453646, "Pos_1:Pos_2_AC": 0.0, "Pos_0:Pos_1:Pos_2_CGA": -0.05579478844496769, "Pos_1:Pos_2:Pos_3_CCG": 0.0, "Pos_0:Pos_1_AC": -0.09801145337344185, "Pos_1:Pos_2_CG": -0.14753106818057443, "Pos_1:Pos_2:Pos_3_GAG": 0.0, "Pos_0:Pos_3_TA": 0.0037005691987188603, "Pos_0:Pos_1:Pos_3_GCT": 0.0, "Pos_0:Pos_2:Pos_3_GGA": -5.893366813245415e-06, "Pos_0:Pos_2_CA": -0.06401114000787828, "Pos_1:Pos_2:Pos_3_CAA": 0.0, "Pos_1:Pos_2_GC": 0.062166591081347845, "Pos_0:Pos_1:Pos_2_TGC": 0.0, "Pos_0:Pos_2:Pos_3_TGA": 0.0, "Pos_1:Pos_2:Pos_3_CGA": 0.0, "CtoA": 0.0, "Pos_0:Pos_1:Pos_2_GTC": 0.0, "Pos_0:Pos_2:Pos_3_GAT": 0.0, "Pos_0:Pos_1:Pos_2_CAG": 0.0, "Pos_1:Pos_3_AT": 0.0, "Pos_0:Pos_2:Pos_3_CAC": -0.3610537748354045, "Pos_0:Pos_1:Pos_2_GTG": 0.0, "Pos_0:Pos_1:Pos_3_TTT": 0.13482853332909073, "Pos_1:Pos_2:Pos_3_GCT": 0.0, "Pos_1:Pos_2:Pos_3_CTC": 0.0, "Pos_3_G": 0.0, "Pos_0:Pos_1:Pos_2_TCC": 0.0, "Pos_0:Pos_2:Pos_3_ATT": 0.0, "Pos_1:Pos_2:Pos_3_TCT": 0.0, "Pos_0:Pos_1:Pos_3_TCT": 0.0, "Pos_0:Pos_1:Pos_3_AGG": 0.4043680417864326, "Pos_2_C": 0.18988646160878198, "Pos_1:Pos_2_CA": 0.0, "Pos_1:Pos_2:Pos_3_TAG": 0.0, "Pos_1:Pos_3_TG": 0.0, "Pos_0:Pos_2_TC": 0.0, "Pos_0:Pos_1:Pos_2_CGC": 0.0, "Pos_1:Pos_3_TA": 0.0, "Pos_0:Pos_2:Pos_3_CGA": 0.0, "Pos_0:Pos_2:Pos_3_CGT": 0.0, "Pos_0:Pos_2:Pos_3_GAG": 0.0, "Pos_0:Pos_1:Pos_3_ATG": 0.509940868608288, "Pos_1:Pos_2:Pos_3_TGC": 0.0, "Pos_0:Pos_1:Pos_2_GGA": 0.0, "Pos_0:Pos_1:Pos_3_CTA": 0.0, "Pos_1:Pos_2:Pos_3_TTC": -0.1165895402635538, "Pos_0:Pos_1:Pos_2_GTA": 0.0, "Pos_1:Pos_2:Pos_3_GAA": 0.0, "Pos_0:Pos_1:Pos_3_AGA": 0.04126754262884453, "Pos_0:Pos_3_AG": 0.11455284417056354, "Pos_1:Pos_2_TC": 0.0, "Pos_0:Pos_1:Pos_3_ATT": 0.0, "TtoG": 0.3136325349267787, "Pos_0:Pos_1:Pos_2_CCG": -0.2777265287212097, "Pos_1:Pos_2:Pos_3_ATC": 0.0, "Pos_0:Pos_1:Pos_2_CCC": 0.0, "AtoT": 0.9285574365238373, "Pos_0:Pos_2:Pos_3_GGT": 0.0, "Pos_2:Pos_3_AT": 0.0, "Pos_0:Pos_1:Pos_3_GTC": 0.31486753620944113, "Pos_0:Pos_2:Pos_3_TCA": 0.0, "Pos_0:Pos_1:Pos_3_CAT": 0.23271847010334235, "Pos_1_A": 0.0, "Pos_0:Pos_1:Pos_3_ATA": -0.25711396200536824, "GtoT": 0.4366641550817043, "Pos_0:Pos_1:Pos_3_ACA": 0.2515987953201169, "Pos_0:Pos_1:Pos_2_ATG": -0.015027680849472445, "Pos_0:Pos_2:Pos_3_GGC": 0.14672762905104228, "Pos_0:Pos_1:Pos_2_ACG": 0.0, "Pos_0:Pos_1:Pos_3_ACT": 0.0, "Pos_1:Pos_3_GA": 0.0, "Pos_0:Pos_1:Pos_3_TCC": 0.0, "Pos_0:Pos_1:Pos_2_AAG": -0.10603695885636251, "Pos_0:Pos_1_GC": 0.0, "Pos_0:Pos_1:Pos_2_CAA": 0.0, "Pos_0:Pos_3_GA": 0.0, "Pos_0:Pos_1:Pos_3_TTC": -0.005187859182026906, "Pos_0:Pos_1:Pos_2_GCT": 0.1843949886006678, "Pos_0:Pos_1:Pos_2_ATC": 0.2114378305051549, "Pos_0:Pos_3_AA": 0.0, "Pos_1:Pos_2:Pos_3_AAA": 0.40896982410546023, "Pos_0:Pos_1_TT": -0.046953487486972714, "Pos_0:Pos_2:Pos_3_ACC": 0.0, "Pos_1:Pos_2:Pos_3_GGT": 0.15839371576178674, "Pos_0:Pos_2:Pos_3_CCA": 0.0, "Pos_0:Pos_1:Pos_2_GCA": 0.13862186568650647, "Pos_1:Pos_2:Pos_3_CCC": -0.0636311231750566, "Pos_2:Pos_3_TA": 0.0, "Pos_1:Pos_2_CT": 0.0018691697714314512, "Pos_0:Pos_2:Pos_3_TGT": 0.28768153557455667, "Pos_0:Pos_1:Pos_2_GTT": 0.0, "Pos_0:Pos_2:Pos_3_GTT": 0.0, "Pos_0:Pos_2:Pos_3_GTA": 0.0, "Pos_0:Pos_1_AA": 0.0, "Pos_0:Pos_1:Pos_3_GCC": -0.2221685575748183, "Pos_2:Pos_3_CG": 0.0, "Pos_0:Pos_2_CG": 0.0, "Pos_0:Pos_1:Pos_3_AGT": 0.0, "Pos_0:Pos_1:Pos_2_GGG": 0.0, "Pos_0:Pos_3_TG": -0.020665052467253645, "Pos_0:Pos_1:Pos_2_TGG": 0.0, "AtoG": 0.3114258570802457, "Pos_0:Pos_1:Pos_2_TCG": 0.20944325275865033, "Pos_0:Pos_1_GT": 0.0, "Pos_0:Pos_2_AC": 0.0, "Pos_0:Pos_1_CG": -0.15603853809125204, "Pos_0:Pos_2_AA": 0.0, "Pos_0:Pos_3_GT": 0.0, "Pos_1:Pos_2:Pos_3_ATG": 0.08023541623403191, "Pos_1:Pos_2:Pos_3_TAA": 0.0, "Pos_0:Pos_1:Pos_2_ACC": 0.0, "Pos_2_T": 0.20204845668632648, "Pos_1:Pos_2:Pos_3_AAT": 0.2704970563261478, "Pos_0:Pos_1_GG": 0.30425837616307916, "Pos_0:Pos_2:Pos_3_AGA": 0.08723710550224548, "Pos_1:Pos_2:Pos_3_CGG": 0.0, "Pos_0:Pos_1:Pos_3_TGA": 0.0, "Pos_0:Pos_3_CA": -0.20178219970242525, "Pos_0:Pos_1:Pos_2_GCG": -0.5330633197268565, "Pos_0:Pos_1:Pos_3_GTT": 0.0, "Pos_1:Pos_2:Pos_3_TGG": 0.0, "Pos_0:Pos_2_TG": 0.0, "Pos_0:Pos_1:Pos_3_GAC": 0.0, "Pos_0:Pos_1:Pos_2_AAA": 0.12815460174905927, "Pos_0:Pos_2_GC": 0.0, "Pos_0:Pos_2:Pos_3_TGC": -0.10000350497386845, "Pos_1:Pos_2:Pos_3_ACA": 0.0, "Pos_0:Pos_2:Pos_3_CGG": 0.0, "Pos_0:Pos_1:Pos_3_CAA": 0.4026718889477875, "Pos_1:Pos_2:Pos_3_TCA": -0.10184381540975798, "Pos_0:Pos_2:Pos_3_AGC": -0.05820420423621526, "Pos_1:Pos_2_TG": 0.016544236766062387, "Pos_0:Pos_1:Pos_2_TTC": -0.0887555168761105, "Pos_0:Pos_1:Pos_3_GTA": 0.0, "Pos_1:Pos_2:Pos_3_CTA": 0.2936572436373851, "Pos_1:Pos_2:Pos_3_ATA": 0.0, "Pos_2:Pos_3_CA": 0.16508200436105191, "Pos_1:Pos_2:Pos_3_TTG": 0.0, "Pos_0:Pos_1:Pos_3_ACG": -0.22034171519183238, "Pos_1:Pos_3_GT": 0.162849455408312, "Pos_0:Pos_2:Pos_3_GCG": 0.0, "Pos_0:Pos_1:Pos_3_CGT": 0.0, "Pos_1:Pos_3_TC": 0.0, "Pos_1:Pos_2:Pos_3_GCA": 0.127792445707756, "Pos_1:Pos_3_CT": 0.0, "Pos_2_G": -0.13898596633067048, "Pos_0:Pos_1:Pos_2_GCC": -0.10853415405139835, "Pos_1_G": 0.0, "Pos_0:Pos_2:Pos_3_AAC": 0.04290347397467207, "Pos_1:Pos_2_AT": 0.0, "Pos_0:Pos_1:Pos_2_CAC": 0.0, "Pos_0:Pos_3_AC": 0.0, "Pos_1:Pos_3_AG": 0.0, "Pos_0:Pos_1:Pos_2_TGA": 0.7385202252466816, "Pos_0:Pos_1:Pos_2_GGC": 0.0, "Pos_0:Pos_3_TC": 0.0, "Pos_3_A": -0.07725711697113381, "Pos_0:Pos_1:Pos_3_TAT": -0.2029703394543058, "Pos_1:Pos_2:Pos_3_GAT": 0.0, "Pos_0:Pos_1:Pos_3_CTT": 0.0, "Pos_1:Pos_3_AA": 0.0, "Pos_0:Pos_1:Pos_2_CGG": 0.0, "Pos_1:Pos_2:Pos_3_CAG": 0.0, "Pos_0:Pos_1:Pos_2_TGT": -0.014318451447239838, "Pos_0:Pos_3_GC": 0.0, "Pos_1:Pos_2_GT": 0.0, "Pos_0:Pos_1:Pos_3_AAG": 0.0, "Pos_0:Pos_1:Pos_2_AGC": -0.004490980874893859, "Pos_0:Pos_2:Pos_3_GCC": 0.0, "Pos_1:Pos_2:Pos_3_AGC": -0.23101181978467858, "Pos_2:Pos_3_GC": 0.0, "Pos_1:Pos_2:Pos_3_ACC": 0.09113442698585607, "Pos_0:Pos_1:Pos_2_GGT": 0.0, "Pos_0:Pos_3_CC": 0.0, "Pos_0:Pos_1:Pos_3_ACC": 0.0, "Pos_2:Pos_3_GA": -0.13615524879951987, "Pos_0:Pos_1:Pos_3_CGC": 0.0050444044402465716, "Pos_0:Pos_2:Pos_3_CCT": 0.17476674677690238, "Pos_0:Pos_1:Pos_2_ATA": 0.020797415094787056, "Pos_1:Pos_2:Pos_3_GCG": 0.0, "Pos_1:Pos_3_CG": 0.0, "Pos_0:Pos_1:Pos_3_AAC": 0.08902434016198846, "Pos_0:Pos_2:Pos_3_GCA": 0.3164636121257403, "Pos_0:Pos_2_TA": 0.0, "Pos_0:Pos_1_AT": 0.0, "Pos_0:Pos_3_TT": 0.09108660783435492, "Pos_0:Pos_1:Pos_3_TCG": -0.05364561699322251, "Pos_0:Pos_1_AG": 0.0, "Pos_0:Pos_1:Pos_3_CGA": -0.7727180988693, "Pos_2_A": 0.0, "Pos_1:Pos_2:Pos_3_ACT": 0.0, "Pos_0:Pos_1:Pos_3_TAA": 0.20293942975374496, "Pos_1:Pos_2:Pos_3_AGA": 0.0, "Pos_0:Pos_1:Pos_2_AAC": 0.0, "Pos_0:Pos_1:Pos_2_AGA": 0.0, "Pos_1:Pos_2:Pos_3_CCA": 0.0617023331284839, "Pos_1:Pos_2_AA": 0.05431438857179967, "Pos_1:Pos_2_TT": 0.0, "Pos_1:Pos_2:Pos_3_GTC": 0.09811249793216935, "Pos_1:Pos_2:Pos_3_TCC": 0.2279744254414753, "Pos_0:Pos_2:Pos_3_CTT": 0.0, "Pos_1:Pos_2:Pos_3_CTT": 0.0, "Pos_2:Pos_3_GT": 0.0, "Pos_0:Pos_1:Pos_3_GCA": 0.0, "Pos_0:Pos_1:Pos_2_AAT": 0.0996407552108055, "CtoT": -0.4118513852144564, "Pos_1:Pos_2:Pos_3_GAC": 0.0, "Pos_0:Pos_2:Pos_3_ACG": 0.0, "Pos_0:Pos_2:Pos_3_GCT": -0.1791625027113643, "Pos_0:Pos_1:Pos_3_TCA": 0.0, "Pos_0:Pos_1:Pos_2_ATT": 0.0, "Pos_0:Pos_1:Pos_2_GAC": 0.0, "Pos_0:Pos_1:Pos_3_ATC": 0.27836224056148084, "Pos_0:Pos_1:Pos_2_TCA": 0.0, "Pos_0:Pos_1:Pos_2_CTC": 0.0, "Pos_0:Pos_2:Pos_3_TAT": 0.0, "Pos_0:Pos_1:Pos_2_TAT": 0.0, "Pos_0:Pos_1:Pos_2_AGG": 0.0, "Pos_1:Pos_2:Pos_3_GTG": -0.07501580607635394, "Pos_0:Pos_1:Pos_2_CTA": 0.0, "Pos_0:Pos_1:Pos_2_GAG": 0.15884976379257856, "Pos_0:Pos_1:Pos_2_TTT": 0.0, "Pos_0:Pos_2:Pos_3_AGT": 0.0, "Pos_0:Pos_2:Pos_3_CGC": 0.02987613881034153, "Pos_0:Pos_2:Pos_3_GAA": 0.0, "Pos_0:Pos_1:Pos_3_TGT": 0.0, "Pos_0:Pos_1:Pos_3_CTC": 0.0, "Pos_0:Pos_1:Pos_2_CCT": 0.0, "Pos_0:Pos_2:Pos_3_ACA": 0.0, "Pos_0_G": 0.0, "Pos_1:Pos_3_TT": 0.0, "Pos_0:Pos_2:Pos_3_GAC": -0.03073241037822691, "Pos_1:Pos_2:Pos_3_GCC": 0.0, "Pos_0:Pos_1:Pos_3_CCG": 0.11983445635297024, "Pos_0:Pos_2:Pos_3_TGG": 0.0, "Pos_1_T": 0.0, "Pos_0:Pos_1:Pos_3_CTG": 0.13487225451575902, "Pos_0:Pos_1:Pos_3_CCA": -0.1499963089166509, "Pos_1:Pos_2:Pos_3_TTT": 0.32982159553913454, "Pos_1:Pos_2:Pos_3_TCG": -0.7426994420640811, "Pos_0:Pos_2:Pos_3_CCG": 0.0, "Pos_0:Pos_1:Pos_3_CAC": -0.11705973762468833, "Pos_0:Pos_1:Pos_2_TTA": -0.2111369523146748, "Pos_0:Pos_2_GA": 0.0, "GtoC": -1.994216794149659, "Pos_1_C": 0.0}